<metadata xml:lang="en"><Esri><CreaDate>20150928</CreaDate><CreaTime>10003600</CreaTime><ArcGISFormat>1.0</ArcGISFormat><SyncOnce>FALSE</SyncOnce><DataProperties><lineage><Process ToolSource="c:\program files (x86)\arcgis\desktop10.2\ArcToolbox\Toolboxes\Data Management Tools.tbx\CalculateField" Date="20150928" Time="100036" Name="" export="">CalculateField Export_Output c [Ckey] VB #</Process><Process ToolSource="c:\program files (x86)\arcgis\desktop10.2\ArcToolbox\Toolboxes\Data Management Tools.tbx\CalculateField" Date="20150928" Time="100103" Name="" export="">CalculateField Export_Output Ckey [c] VB #</Process><Process ToolSource="c:\program files (x86)\arcgis\desktop10.3\ArcToolbox\Toolboxes\Data Management Tools.tbx\CalculateField" Date="20160607" Time="175458">CalculateField JMM_B24_J93 sheet 1 VB #</Process><Process ToolSource="c:\program files (x86)\arcgis\desktop10.3\ArcToolbox\Toolboxes\Data Management Tools.tbx\CalculateField" Date="20160607" Time="175506">CalculateField JMM_B24_J93 web_map "http://stanford.maps.arcgis.com/apps/SimpleViewer/index.html?appid=f9c44d92beda42a0b633209cdb6e8b88" VB #</Process><Process ToolSource="c:\program files (x86)\arcgis\desktop10.3\ArcToolbox\Toolboxes\Data Management Tools.tbx\CalculateField" Date="20160607" Time="175526">CalculateField JMM_B24_J93 sheet 0 VB #</Process><Process ToolSource="c:\program files (x86)\arcgis\desktop10.3\ArcToolbox\Toolboxes\Data Management Tools.tbx\CalculateField" Date="20160607" Time="175603">CalculateField JMM_B24_J93 web_map "http://stanford.maps.arcgis.com/apps/SimpleViewer/index.html?appid=caacd5d6591041e99a9fc40a70933bd2" VB #</Process><Process ToolSource="c:\program files (x86)\arcgis\desktop10.3\ArcToolbox\Toolboxes\Data Management Tools.tbx\Dissolve" Date="20160607" Time="175736">Dissolve "JMM_B24_J93 selection" Q:\SGC_Index_Maps\Competed_IndexMaps\JMM_B24_J93\JMM_B24_J93_boundary.shp # "Call_Short FIRST;Label FIRST;Title FIRST;Ckey FIRST;sheet SUM;web_map FIRST" MULTI_PART DISSOLVE_LINES</Process></lineage><itemProps><itemName Sync="TRUE">JMM_B24_J93_boundary</itemName><imsContentType Sync="TRUE">002</imsContentType><nativeExtBox><westBL Sync="TRUE">130.500000</westBL><eastBL Sync="TRUE">141.000000</eastBL><southBL Sync="TRUE">-4.666667</southBL><northBL Sync="TRUE">-0.666667</northBL><exTypeCode Sync="TRUE">1</exTypeCode></nativeExtBox><itemSize Sync="TRUE">0.000</itemSize><itemLocation><linkage Sync="TRUE">file://\\sul-gislab\GIS_Shared\SGC_Index_Maps\Competed_IndexMaps\JMM_B24_J93\JMM_B24_J93_boundary.shp</linkage><protocol Sync="TRUE">Local Area Network</protocol></itemLocation></itemProps><coordRef><type Sync="TRUE">Geographic</type><geogcsn Sync="TRUE">GCS_WGS_1984</geogcsn><csUnits Sync="TRUE">Angular Unit: Degree (0.017453)</csUnits><peXml Sync="TRUE">&lt;GeographicCoordinateSystem xsi:type='typens:GeographicCoordinateSystem' xmlns:xsi='http://www.w3.org/2001/XMLSchema-instance' xmlns:xs='http://www.w3.org/2001/XMLSchema' xmlns:typens='http://www.esri.com/schemas/ArcGIS/10.3'&gt;&lt;WKT&gt;GEOGCS[&amp;quot;GCS_WGS_1984&amp;quot;,DATUM[&amp;quot;D_WGS_1984&amp;quot;,SPHEROID[&amp;quot;WGS_1984&amp;quot;,6378137.0,298.257223563]],PRIMEM[&amp;quot;Greenwich&amp;quot;,0.0],UNIT[&amp;quot;Degree&amp;quot;,0.0174532925199433],AUTHORITY[&amp;quot;EPSG&amp;quot;,4326]]&lt;/WKT&gt;&lt;XOrigin&gt;-400&lt;/XOrigin&gt;&lt;YOrigin&gt;-400&lt;/YOrigin&gt;&lt;XYScale&gt;11258999068426.238&lt;/XYScale&gt;&lt;ZOrigin&gt;-100000&lt;/ZOrigin&gt;&lt;ZScale&gt;10000&lt;/ZScale&gt;&lt;MOrigin&gt;-100000&lt;/MOrigin&gt;&lt;MScale&gt;10000&lt;/MScale&gt;&lt;XYTolerance&gt;8.983152841195215e-009&lt;/XYTolerance&gt;&lt;ZTolerance&gt;0.001&lt;/ZTolerance&gt;&lt;MTolerance&gt;0.001&lt;/MTolerance&gt;&lt;HighPrecision&gt;true&lt;/HighPrecision&gt;&lt;LeftLongitude&gt;-180&lt;/LeftLongitude&gt;&lt;WKID&gt;4326&lt;/WKID&gt;&lt;LatestWKID&gt;4326&lt;/LatestWKID&gt;&lt;/GeographicCoordinateSystem&gt;</peXml></coordRef></DataProperties><SyncDate>20160607</SyncDate><SyncTime>17573500</SyncTime><ModDate>20160607</ModDate><ModTime>17573500</ModTime><scaleRange><minScale>150000000</minScale><maxScale>5000</maxScale></scaleRange><ArcGISProfile>ItemDescription</ArcGISProfile></Esri><dataIdInfo><envirDesc Sync="TRUE">Microsoft Windows 7 Version 6.1 (Build 7601) Service Pack 1; Esri ArcGIS 10.3.1.4959</envirDesc><dataLang><languageCode value="eng" Sync="TRUE"/><countryCode value="USA" Sync="TRUE"/></dataLang><idCitation><resTitle Sync="FALSE">Papua, Indonesia 1:100,000 Maps Index</resTitle><presForm><PresFormCd value="005" Sync="TRUE"/></presForm></idCitation><spatRpType><SpatRepTypCd value="001" Sync="TRUE"/></spatRpType><dataExt><geoEle xmlns=""><GeoBndBox esriExtentType="search"><exTypeCode Sync="TRUE">1</exTypeCode><westBL Sync="TRUE">130.500000</westBL><eastBL Sync="TRUE">141.000000</eastBL><northBL Sync="TRUE">-0.666667</northBL><southBL Sync="TRUE">-4.666667</southBL></GeoBndBox></geoEle></dataExt><idPurp>This layer provides an index map that can be used to locate individual scanned map sheets.</idPurp><idAbs>&lt;DIV STYLE="text-align:Left;"&gt;&lt;DIV&gt;&lt;DIV&gt;&lt;P&gt;&lt;SPAN&gt;This polygon shapefile is an index to 1:100,000 scale maps of Papua, Indonesia, titled 'Kūchū shashin sokuzu yōzu Seibu Papua jūmanbun no ichi -- Seibu Papua jūmanbun no ichi -- 空中寫真測圖要圖西部パプア十万分一 -- 西部パプア十万分一/Kūchū shashin sokuzu yōzu Seibu Papua jūmanbun no ichi.' To create this index, footprints were generated using the fishnet tool, and metadata were supplied for the digitized paper maps by Stanford University Libraries. After the footprints were created, the shapefile was trimmed and labeled according to the sources.&lt;/SPAN&gt;&lt;/P&gt;&lt;/DIV&gt;&lt;/DIV&gt;&lt;/DIV&gt;</idAbs><idCredit>Stanford University Libraries, Stanford Geospatial Center</idCredit><searchKeys><keyword>Grids (Cartography)</keyword><keyword>Index Maps</keyword><keyword>Papua</keyword><keyword>Indonesia</keyword></searchKeys></dataIdInfo><mdLang><languageCode value="eng" Sync="TRUE"/><countryCode value="USA" Sync="TRUE"/></mdLang><mdChar><CharSetCd value="004" Sync="TRUE"/></mdChar><distInfo><distFormat><formatName Sync="TRUE">Shapefile</formatName></distFormat><distTranOps><transSize Sync="TRUE">0.000</transSize></distTranOps></distInfo><mdHrLv><ScopeCd value="005" Sync="TRUE"/></mdHrLv><mdHrLvName Sync="TRUE">dataset</mdHrLvName><refSysInfo><RefSystem><refSysID><identCode code="4326" Sync="TRUE"/><idCodeSpace Sync="TRUE">EPSG</idCodeSpace><idVersion Sync="TRUE">8.6.2</idVersion></refSysID></RefSystem></refSysInfo><spatRepInfo><VectSpatRep><geometObjs Name="JMM_B24_J93_boundary"><geoObjTyp><GeoObjTypCd value="002" Sync="TRUE"></GeoObjTypCd></geoObjTyp><geoObjCnt Sync="TRUE">0</geoObjCnt></geometObjs><topLvl><TopoLevCd value="001" Sync="TRUE"></TopoLevCd></topLvl></VectSpatRep></spatRepInfo><spdoinfo><ptvctinf><esriterm Name="JMM_B24_J93_boundary"><efeatyp Sync="TRUE">Simple</efeatyp><efeageom code="4" Sync="TRUE"></efeageom><esritopo Sync="TRUE">FALSE</esritopo><efeacnt Sync="TRUE">0</efeacnt><spindex Sync="TRUE">FALSE</spindex><linrefer Sync="TRUE">FALSE</linrefer></esriterm></ptvctinf></spdoinfo><eainfo><detailed Name="JMM_B24_J93_boundary"><enttyp><enttypl Sync="TRUE">JMM_B24_J93_boundary</enttypl><enttypt Sync="TRUE">Feature Class</enttypt><enttypc Sync="TRUE">0</enttypc></enttyp><attr><attrlabl Sync="TRUE">FID</attrlabl><attalias Sync="TRUE">FID</attalias><attrtype Sync="TRUE">OID</attrtype><attwidth Sync="TRUE">4</attwidth><atprecis Sync="TRUE">0</atprecis><attscale Sync="TRUE">0</attscale><attrdef Sync="TRUE">Internal feature number.</attrdef><attrdefs Sync="TRUE">Esri</attrdefs><attrdomv><udom Sync="TRUE">Sequential unique whole numbers that are automatically generated.</udom></attrdomv></attr><attr><attrlabl Sync="TRUE">Shape</attrlabl><attalias Sync="TRUE">Shape</attalias><attrtype Sync="TRUE">Geometry</attrtype><attwidth Sync="TRUE">0</attwidth><atprecis Sync="TRUE">0</atprecis><attscale Sync="TRUE">0</attscale><attrdef Sync="TRUE">Feature geometry.</attrdef><attrdefs Sync="TRUE">Esri</attrdefs><attrdomv><udom Sync="TRUE">Coordinates defining the features.</udom></attrdomv></attr><attr><attrlabl Sync="TRUE">FIRST_Call</attrlabl><attalias Sync="TRUE">FIRST_Call</attalias><attrtype Sync="TRUE">String</attrtype><attwidth Sync="TRUE">50</attwidth><atprecis Sync="TRUE">0</atprecis><attscale Sync="TRUE">0</attscale></attr><attr><attrlabl Sync="TRUE">FIRST_Labe</attrlabl><attalias Sync="TRUE">FIRST_Labe</attalias><attrtype Sync="TRUE">String</attrtype><attwidth Sync="TRUE">254</attwidth><atprecis Sync="TRUE">0</atprecis><attscale Sync="TRUE">0</attscale></attr><attr><attrlabl Sync="TRUE">FIRST_Titl</attrlabl><attalias Sync="TRUE">FIRST_Titl</attalias><attrtype Sync="TRUE">String</attrtype><attwidth Sync="TRUE">254</attwidth><atprecis Sync="TRUE">0</atprecis><attscale Sync="TRUE">0</attscale></attr><attr><attrlabl Sync="TRUE">FIRST_Ckey</attrlabl><attalias Sync="TRUE">FIRST_Ckey</attalias><attrtype Sync="TRUE">String</attrtype><attwidth Sync="TRUE">50</attwidth><atprecis Sync="TRUE">0</atprecis><attscale Sync="TRUE">0</attscale></attr><attr><attrlabl Sync="TRUE">SUM_sheet</attrlabl><attalias Sync="TRUE">SUM_sheet</attalias><attrtype Sync="TRUE">Double</attrtype><attwidth Sync="TRUE">19</attwidth><atprecis Sync="TRUE">0</atprecis><attscale Sync="TRUE">0</attscale></attr><attr><attrlabl Sync="TRUE">FIRST_web_</attrlabl><attalias Sync="TRUE">FIRST_web_</attalias><attrtype Sync="TRUE">String</attrtype><attwidth Sync="TRUE">100</attwidth><atprecis Sync="TRUE">0</atprecis><attscale Sync="TRUE">0</attscale></attr></detailed></eainfo><mdDateSt Sync="TRUE">20160607</mdDateSt><Binary><Thumbnail><Data EsriPropertyType="PictureX">/9j/4AAQSkZJRgABAQEAYABgAAD/2wBDAAMCAgMCAgMDAwMEAwMEBQgFBQQEBQoHBwYIDAoMDAsK
CwsNDhIQDQ4RDgsLEBYQERMUFRUVDA8XGBYUGBIUFRT/2wBDAQMEBAUEBQkFBQkUDQsNFBQUFBQU
FBQUFBQUFBQUFBQUFBQUFBQUFBQUFBQUFBQUFBQUFBQUFBQUFBQUFBQUFBT/wAARCAM9BKYDASIA
AhEBAxEB/8QAHwAAAQUBAQEBAQEAAAAAAAAAAAECAwQFBgcICQoL/8QAtRAAAgEDAwIEAwUFBAQA
AAF9AQIDAAQRBRIhMUEGE1FhByJxFDKBkaEII0KxwRVS0fAkM2JyggkKFhcYGRolJicoKSo0NTY3
ODk6Q0RFRkdISUpTVFVWV1hZWmNkZWZnaGlqc3R1dnd4eXqDhIWGh4iJipKTlJWWl5iZmqKjpKWm
p6ipqrKztLW2t7i5usLDxMXGx8jJytLT1NXW19jZ2uHi4+Tl5ufo6erx8vP09fb3+Pn6/8QAHwEA
AwEBAQEBAQEBAQAAAAAAAAECAwQFBgcICQoL/8QAtREAAgECBAQDBAcFBAQAAQJ3AAECAxEEBSEx
BhJBUQdhcRMiMoEIFEKRobHBCSMzUvAVYnLRChYkNOEl8RcYGRomJygpKjU2Nzg5OkNERUZHSElK
U1RVVldYWVpjZGVmZ2hpanN0dXZ3eHl6goOEhYaHiImKkpOUlZaXmJmaoqOkpaanqKmqsrO0tba3
uLm6wsPExcbHyMnK0tPU1dbX2Nna4uPk5ebn6Onq8vP09fb3+Pn6/9oADAMBAAIRAxEAPwD7Vooo
rUAooooAKKKKACiiigAooooAKKKKACiiigAooooAKKKKACiiigAooooAKKKKACiiigAooooAKKKK
ACiiigAooooAKKKKACiiigAooooAKKKKACiiigAooooAKKKKACiiigAooooAKKKKACiiigAooooA
KKKKACiiigAooooAKKKKACiiigAooooAKKKKACiiigAooooAKKKKACiiigAooooAKKKKACiiigAo
oooAKKKKACiiigAooooAKKKKACiiigAooooAKKKKACiiigAooooAKKKKACiiigAooooAKKKKACii
igAooooAKKKKACiiigAooooAKKKKACiiigAooooAKKKKACiiigAooooAKKKKACiiigAooooAKKKK
ACiiigAooooAKKKKACiiigAooooAKKKKACiiigAooooAKKKKACiiigAooooAKKKKACiiigAooooA
KKKKACiiigAooooAKKKKACiiigAooooAKKKKACiiigAooooAKKKKACiiigAooooAKKKKACiiigAo
oooAKKKKACiiigAooooAKKKKACiiigAooooAKKKKACiiigAooooAKKKKACiiigAooooAKKKKACii
igAooooAKKKKACiiigAooooAKKKKACiiigAooooAKKKKACiiigAooooAKKKKACiiigAooooAKKKK
ACiiigAooooAKKKKACiiigAooooAKKKKACiiigAooooAKKKKACiiigAooooAKKKKACiiigAooooA
KKKKACiiigAooooAKKKKACiiigAooooAKKKKACiiigAooooAKKKKACiiigAooooAKKKKACiiigAo
oooAKKKKACiiigAooooAKKKKACiiigAooooAKKKKACiiigAooooAKKKKACiiigAooooAKKKKACii
igAooooAKKKKACiiigAooooAKKKKACiiigAooooAKKKKACiiigAooooAKKKKACiiigAooooAKKKK
ACiiigAooooAKKKKACiiigAooooAKKKKACiiigAooooAKKKKACiiigAooooAKKKKACiiigAooooA
KKKKACiiigAooooAKKKKACiiigAooooAKKKKACiiigAooooAKKKKACiiigAooooAKKKKACiiigAo
oooAKKKKACiiigAooooAKKKKACiiigAooooAKKKKACiiigAooooAKKKKACiiigAooooAKKKKACii
igAooooAKKKKACiiigAooooAKKKKACiiigAooooAKKKKACiiigAooooAKKKKACiiigAooooAKKKK
ACiiigAooooAKKKKACiiigAooooAKKKKACiiigAooooAKKKKACiiigAooooAKKKKACiiigAooooA
KKKKACiiigAooooAKKKKACiiigAooooAKKKKACiiigAooooAKKKKACiiigAooooAKKKKACiiigAo
oooAKKKKACiiigAooooAKKKKACiiigAooooAKKKKACiiigAooooAKKKKACiiigAooooAKKKKACii
igAooooAKKKKACiiigAooooAKKKKACiiigAooooAKKKKACiiigAooooAKKKKACiiigAooooAKKKK
ACiiigAooooAKKKKACiiigAooooAKKKKACiiigAooooAKKKKACiiigAooooAKKKKACiiigAooooA
KKKKACiiigAooooAKKKKACiiigAooooAKKKKACiiigAooooAKKKKACiiigAooooAKKKKACiiigAo
oooAKKKKACiiigAooooAKKKKACiiigAooooAKKKKACiiigAooooAKKKKACiiigAooooAKKKKACii
igAooooAKKKKACiiigAooooAKKKKACiiigAooooAKKKKACiiigAooooAKKKKACiiigAooooAKKKK
ACiiigAooooAKKKKACiiigAooooAKKKKACiiigAooooAKKKKACiiigAooooAKKKKACiiigAooooA
KKKKACiiigAooooAKKKKACiiigAooooAKKKKACiiigAooooAKKKKACiiigAooooAKKKKACiiigAo
oooAKKKKACiiigAooooAKKKKACiiigAooooAKKKKACiiigAooooAKKKKACiiigAooooAKKKKACii
igAooooAKKKKACiiigAooooAKKKKACiiigAooooAKKKKACiiigAooooAKKKKACiiigAooooAKKKK
ACiiigAooooAKKKKACiiigAooooAKKKKACiiigAooooAKKKKACiiigAooooAKKKKACiiigAooooA
KKKKACiiigAooooAKKKKACiiigAooooAKKKKACiiigAooooAKKKKACiiigAooooAKKKKACiiigAo
oooAKKKKACiiigAooooAKKKKACiiigAooooAKKKKACiiigAooooAKKKKACiiigAooooAKKKKACii
igAooooAKKKKACiiigAooooAKKKKACiiigAooooAKKKKACiiigAooooAKKKKACiiigAooooAKKKK
ACiiigAooooAKKKKACiiigAooooAKKKKACiiigAooooAKKKKACiiigAooooAKKKKACiiigAooooA
KKKKACiiigAooooAKKKKACiiigAooooAKKKKACiiigAooooAKKKKACiiigAooooAKKKKACiiigAo
oooAKKKKACiiigAooooAKKKKACiiigAooooAKKKKACiiigAooooAKKKKACiiigAooooAKKKKACii
igAooooAKKKKACiiigAooooAKKKKACiiigAooooAKKKKACiiigAooooAKKKKACil+oxSUAFFKFLM
ABk9hRtPI9OvtQAlFWrPTZ71wkaHPXc2cVatfDt1dO6bNrL/AHicdTQBl0VuL4RvfMUMUVT1YHOK
vN4VELQmFBcMD83mPhT+VK4HLbT1wfypK9ItrSMQqJLWKM9NgGR+dNm0WyuVIa2QD1UYNFwPOaK6
m98G7Uc283P8KN9abH4RENq8kxd5sHCRcii6A5iircml3caqWt3APqDmqzIyNtYFT6EYNMBtFFFA
BRRRQAUUUUAFFFFABRRRQAUUUUAFFFFABRRRQAUUUUAFFFFABRRRQAUUUUAFFFFABRRRQAUUUUAF
FFFABRRRQAUUUUAFFFFABRRRQAUUUUAFFFFABRRRQAUUUUAFFFFABRRRQAUUUUAFFFFABRRRQAUU
UUAFFFFABRRRQAUUUUAFFFFABRRRQAUUUUAFFFFABRRRQAUUUUAFFFFABRRRQAUUUUAFFFFABRRR
QAUUUUAFFFFABRRRQAUUUUAFFFFABRRRQAUUUUAFFFFABRRRQAUUUUAFFFFABRRRQAUUUUAFFFFA
BRRRQAUUUUAFFFFABRRRQAUUUUAFFFFABRRRQAUUUUAFFFFABRRRQAVd0e1ivdQjinbZH1PzYz7V
Vij8yRE3Bdx6ntWiNDvoZFeJFlwdylDnNAG5PokVjJG1m6rKJFLB25Az2q3/AGTBNqkrybtxQZUD
CH8e9ZUkeqajab5bfZJAdwfGw/lV/R5b+4mSVwnksvVnzn/69QBuJGI41RVCqvAp3rRj2o/WpA43
xFcPayvbo0wXO4sz5BzV7wjqiNbvayyYKnI3HtW9dWqXlu8Mi5VuMelee6hZSaXeGJvlKHKt6j1q
1qB6R/niisHwheTXVnIJCXCNwScnntW9UgFFFFIArH1zQI9SVpUG25HQ9jWxRTA84utIu7RWaSBw
g744qnXqf6nNcJ4nS3XUj5DAk/fUdjVp3Ax6KKKYBRRRQAUUUUAFFFFABRRRQAUUUUAFFFFABRRR
QAUUUUAFFFFABRRRQAUUUUAFFFFABRRRQAUUUUAFFFFABRRRQAUUUUAFFFFABRRRQAUUUUAFFFFA
BRRRQAUUUUAFFFFABRRRQAUUUUAFFFFABRRRQAUUUUAFFFFABRRRQAUUUUAFFFFABRRRQAUUUUAF
FFFABRRRQAUUUUAFFFFABRRRQAUUUUAFFFFABRRRQAUUUUAFFFFABRRRQAUUUUAFFFFABRRRQAUU
UUAFFFFABRRRQAUUUUAFFFFABRRRQAUUUUAFFFFABRRRQAUUUUAFFFFABRRRQAUUUUAFFFFABRRR
QAUUUUAFFFFAFmx02fUpGjgXcVGWHfFQ75IG+VirKR0PIxT7W7ms5N8MhjboSO4qNmMhJbknrQB0
cfjCSPygU3BV+cnqT2NWrfxgks4RotkWD83cVyFH86VkB0jeJrrUryKGBViVnwO5NdcM4AJycCvL
slTuBKmupvbq6g8P23kb1wuZJA3Sk0B00k0duu+Rwi56scVh+KNNW/s0miHmSrjbtGQwrkpLqWXa
JZGkQfw5rvtCaP8AsuAwlvLAz8xzg9xStYDjLVdS0+ZY4hJC8pyBj71XdK1e8tNWCXBZi52srnGK
7IxqzAkDcOh6kVFNY280gd4Vd89SP1o5gJ1YSDKnIPQ0e9Yc3iK3029kt33SJnI2D7vsc1WXxpF5
cu6Jt+cLt6fjSsB0v6HGaK4NvFF+ZjIrhf8AZ7Ve0/xjMZlW6VShON68Yp8rA6/Pcc49K4zxTpMd
tK1yki4b78efmzW7qniCKxjjljCzq/GVNcTfXkl9cPM5+Zjx7U0gK/60Uvt2pKoAooooAKKKKACi
iigAoopaAEooo/GgAo7inbW/umtCz0C9vMbYSiN/G3SgDNoroZvBl0nMcsb+2Tn+VV/+EU1DaT5a
/TdSugMaitNvDeorGWNuQB7ioH0e9jkCG2k3HkcUwKdFOkjaJirqVcdV7im0AFFFFABRRRQAUUUU
AFFFFABRRRQAUUUUAFFFFABRRRQAUUUUAFFFFABRRRQAUUUUAFFFFABRRRQAUUUUAFFFFABRRRQA
UUUUAFFFFABRRRQAUUUUAFFFFABRRRQAUUUUAFFFFABRRRQAUUUUAFFFFABRRRQAUUUUAFFFFABR
RRQAUUUUAFFFFABRRRQAUUUUAFFFFABRRRQAUUUUAFFFFABRRRQAUUUUAFFFFABRRRQAUUUUAFFF
FABRRRQAUUUUAFFFFABRRRQAUUUUAFFFFABRRRQAUUUUAFFFFABRRRQAUUUUAFFFFABR/Kil9KAL
P9nz/Y/teP3WcV0Wn6X/AGppMEcc7JDndIGXlm9OvTFFnrVvb2YivHgdQB+7hTn8femTao2pX1vD
pxNvGn3m6Dt2qdwJtS8HxtGXtWKSKOUPQ0vh/VobG1azuyIJYmIAP61d1jWYbGyYeerTlcAL1rg3
Z5GLOSWPJPehagd/J4k0+PkzZx/dFYeoeMHmjZLWPymz/rCcnH0rnP5UU7AOklaZ2Z2ZmP8AEeab
SUUwCiiigBdxbAP3fTNJRRTAKKKKQBRRRQAUUUUAFFFFABR7UVs+GtLh1O6cT5KIM49aAKul6RLq
k2yP5Ix1ciuotfCNnBhmeSRwc84x+VbFvbx28eyJFjX/AGRxUlQ2BH9mi/55Jj/dFSAAcDgflRRU
gH44H0ooooAPpQPy/HNFFAFDUNEtdQVgyBHbnzF61yuo+GLqyy8Y8+Md1613NH/6qdwPL5Iniba6
srHnDDBpp4ODwfevTZLSGdg0kSOw6EjJrC1jwqb64aaGRUJH+r21dwOOoq7No95Dv3W77V6ntVP+
WaYCUUUUAFFFFABRRRQAUUUUAFFFFABRRRQAUUUUAFFFFABRRRQAUUUUAFFFFABRRRQAUUUUAFFF
FABRRRQAUUUUAFFFFABRRRQAUUUUAFFFFABRRRQAUUUUAFFFFABRRRQAUUUUAFFFFABRRRQAUUUU
AFFFFABRRRQAUUUUAFFFFABRRRQAUUUUAFFFFABRRRQAUUUUAFFFFABRRRQAUUUUAFFFFABRRRQA
UUUUAFFFFABRRRQAUUUUAFFFFABRRRQAUUUUAFFFFABRRRQAUUUUAFFFFABRRRQAUUUUAFFFFABR
RRQAU5ZGTdtLAN94A1R1TWtP0O3WfUr620+Bm2LLdTLEpbBOAWIGcA8exrL/AOFieFP+hm0f/wAD
4v8A4qgDoKK5/wD4WJ4U/wChm0f/AMD4v/iqP+FieFP+hm0f/wAD4v8A4qgDoKK5/wD4WJ4U/wCh
m0f/AMD4v/iqP+FieFP+hm0f/wAD4v8A4qgDoKK5/wD4WJ4U/wChm0f/AMD4v/iqP+FieFP+hm0f
/wAD4v8A4qgDoKK5/wD4WJ4U/wChm0f/AMD4v/iqP+FieFP+hm0f/wAD4v8A4qgDoKK5/wD4WJ4U
/wChm0f/AMD4v/iqP+FieFP+hm0f/wAD4v8A4qgDoKK5/wD4WJ4U/wChm0f/AMD4v/iqP+FieFP+
hm0f/wAD4v8A4qgDoKK5/wD4WJ4U/wChm0f/AMD4v/iqP+FieFP+hm0f/wAD4v8A4qgDoKK5/wD4
WJ4U/wChm0f/AMD4v/iqP+FieFP+hm0f/wAD4v8A4qgDoKckZkYKoLMemK53/hYnhTr/AMJNo/8A
4Hxf/FV1Hhvx54FtkW5uPF/h/wA49FbU4Bt/8epXA39O8HmRUluZCAedi9a6Sx0+DT4ykEYT1xyf
xNc5/wALa8D/APQ5eH//AAaQf/F0f8La8D/9Dn4f/wDBpB/8XUXA6uiuU/4W14H/AOhz8P8A/g0g
/wDi6P8AhbXgf/oc/D//AINIP/i6QHV0Vyn/AAtrwP8A9Dn4f/8ABpB/8XR/wtrwP/0Ofh//AMGk
H/xdAHV0Vyn/AAtrwP8A9Dn4f/8ABpB/8XXQaXq1jrlhFfabe2+oWUufLubWVZY3wSDhlJBwQR9Q
aALdFFFABRRRQAUUUUAIyh1KsAVIwc1k3HhuykglVIQrNyGyeDWvRTA85vdIutPb97EwUHhscVSr
1JlDKVIyp6iuK1/w69hvnh+a3POAOV9qtMDCooopgFFZeqeKtE0O4WDUtYsNPnZd6xXV0kTFSSMg
MQcZB59jVP8A4WJ4U/6GbR//AAPi/wDiqAOgorn/APhYnhT/AKGbR/8AwPi/+Ko/4WJ4U/6GbR//
AAPi/wDiqAOgorn/APhYnhT/AKGbR/8AwPi/+Ko/4WJ4U/6GbR//AAPi/wDiqAOgorn/APhYnhT/
AKGbR/8AwPi/+Ko/4WJ4U/6GbR//AAPi/wDiqAOgorn/APhYnhT/AKGbR/8AwPi/+Ko/4WJ4U/6G
bR//AAPi/wDiqAOgorn/APhYnhT/AKGbR/8AwPi/+Ko/4WJ4U/6GbR//AAPi/wDiqAOgorn/APhY
nhT/AKGbR/8AwPi/+KqS38eeGry4igg8RaTPPKwSOKO9iZnYnAAAbJJPagDcooooAKKKKACiiigA
orL1TxVomh3CwalrFhp87LvWK6ukiYqSRkBiDjIPPsap/wDCxPCn/QzaP/4Hxf8AxVAHQUVz/wDw
sTwp/wBDNo//AIHxf/FUf8LE8Kf9DNo//gfF/wDFUAdBRXP/APCxPCn/AEM2j/8AgfF/8VW/B4y8
BXmlRlfGGg292epk1OEc/Qv0oAWiqtx4o8IR7fK8beHZc9c6rAMf+P1U/wCEy8L+Yy/8JZ4e4/i/
taDB/wDH6LoDVorE/wCE88LeYyDxTofB6/2lBj893NRH4heFVP8AyM+je/8AxMIv/iqAOgorn/8A
hYnhT/oZtH/8D4v/AIqk/wCFieFP+hm0f/wYQ/8AxVAHQ0Vz/wDwsTwp/wBDNo//AIHxf/FUf8LE
8Kf9DNo//gfF/wDFUAdBRXP/APCxPCn/AEM2j/8AgfF/8VR/wsTwp/0M2j/+B8X/AMVQB0FFc/8A
8LE8Kf8AQzaP/wCB8X/xVH/CxPCn/QzaP/4Hxf8AxVAHQUVz/wDwsTwp/wBDNo//AIHxf/FUf8LE
8Kf9DNo//gfF/wDFUAdBRVPS9a0/XLdp9NvrbUIFbY0trMsqhgAcEqSM4I49xVygAooooAKKKKAC
iiigAooooAKKKKACiiigAooooAKKKKACiiigAooooAKKKKACiiigAooooAKKKKACiiigAooooAKK
KKACiiigAooooAKKKKACiiigAooooAKKKKACiiigAooooAKKKKACiiigAooooAKKKKACiiigAooo
oAKKKKACiiigAoop8UbTSJGv3mIAoAzLj/kcPBX/AGFJf/SC7r1CvPtY0z+z/FfgbeW85tUm3Lt4
H+gXeOa9Brwsd/EXoethPgfqFFFFeedoUUUUAFcv4P8A+Rh8cf8AYYj/APTfZ11FecN4wg8H6p4u
ke1nv7u98Qw2lpZW23zJ5m060IVSxAHCsckgcVpFN3S/rUiTSs2ej0Vm+HtSv9V00XGo6Lc6Dcbi
ptLqaGVxjvmJ2X9a0qhpxdmUmmroKKKKQwrl/ip/yS/xh/2B7z/0Q9dRXL/FT/kl/jD/ALA95/6I
erh8SJl8LOooooqCgooooAKKKKAOX1H/AJKh4f8A+wPqX/o+xrqK5fUf+SoeH/8AsD6l/wCj7Guo
qnsiFuwoooqSwooooAKxfhf/AMivc/8AYY1b/wBONxW1WL8L/wDkV7n/ALDGrf8ApxuK9HBfEzz8
X8KOtooor1zzAooooAKKKKACiiigApJFEilWGQRjFLRQBy2qeEODJZHp/wAsm/pWT/wjOo7d3kfr
Xf0VXMB5l4Qs5rL4ieI45kMbnStOOD6ede13Vc9F/wAlU1//ALAum/8Ao+/roa+fxX8aX9dD2sP/
AAkFFFcg/wAS7CP4oR+Bza3A1CSw/tAXOF8nZuZduc53fL6d65knLY6G0tzr6K5K++JWn2fxM0rw
QIJ5tTv7WW8EsYXyokjUkhznOSBwAO9dbQ01uJNPYK5f4b/8i9d/9hjVf/ThcV1Fcv8ADf8A5F67
/wCwxqv/AKcLin9li+0jqKKw/CviyDxYNYNvBNAumajJpshlx88iRxuWXBPGJV6+hrcpNNaMpNPY
KKKKQwrj/ix/yJ6/9hTTP/S+Cups5priN2mtXtSJGRVkZWLKDgP8pOAeozz6iuW+LH/Inr/2FNM/
9L4K2pfxI+qMqn8OXozPooor6c8EKKKKACiiigA8Df8AJQPEn/YL07/0be16BXn/AIG/5KB4k/7B
enf+jb2vQK+dxX8aX9dD2sP/AAkFFFFch0hRRRQAVy/wr/5Jf4P/AOwPZ/8AohK6iuX+Ff8AyS/w
f/2B7P8A9EJVfZZH2kdRRRRUlhRRRQAVy/jD/kYfA/8A2GJP/TfeV1Fcv4w/5GHwP/2GJP8A033l
VHciWx1FFFFSWFFFFABRRRQB5fb/API4eNf+wpF/6QWlaFZ9v/yOHjX/ALCkX/pBaVoV9PR/hR9E
eBU+OXqFFFFbGYUUUUAFFFFABRRRQAUUUUAFFFFABRRRQAUUUUAFFFFABRRRQAUUUUAFFFFABRRR
QAUUUUAFFFFABRRRQAUUUUAFFFFABRRRQAUUUUAFFFFABRRRQAUUUUAFFFFABRRRQAUUUUAFFFFA
BRRRQAUUUUAFFFFABRRRQAUUUUAFFFFAB+tX9Ks3luElKP5KMCzrgY/OqFTfapTCI/MITOdo4FAG
142kjbXPAoWRXYay/cE/8g+8roK8xupGfxh4K3Nk/wBqSn2/48LuvTq8LG6VF6HrYT4H6hRRRXnn
aFFFFABXlGuWOgahc+Lk17Uxoyx+IoZbS/8ANETQTjTrQKwY8A4LdfU16vXIeG7C11DXPHEd3bQ3
cQ1mM+XcRrIuf7Ps+cEEVpTdrv8Arczmr6HnN54i1LxN4Fs4b2+ku9Gj8SR6bfazbDYLqxC7mlBG
flywQsD1Q1haxpekXniq00fw2yr4ObXdJRnsZ2aIzvNiSNWyc/JtJwTyTX0d9lt/si2ot4VtVGBA
sSiMD02gYplvp9paxxRQWdtBFFIJUjigRVVx0YADGfeuiNaEXsYSpSktzyXxVofh2Hx7Y6P4hjhs
PBVno2+zt552jtjc+btw7FhkhOQCe1cf4N8N2/jbxJ5Oswy3Olx+Hrx7CGSV1V4VvIlglIyDnaci
voq70+11BAl3awXaA5C3ESyL+TA1IsMSvvWGJW8vycrGAQmQdo44GQOPalGslHXf+tRyotvyPB5t
Um174a/CT+155ItA1S4A1yZXKr5K29wyB2/hUypECff3qtpK6Kum/HaHw+wfSbfQ7dIPLkZ4lzBe
lhGSTkcDkE17R4n0G81bR4rHSbyz0oxkbftFgLmDaM/KYtyAjn1Fcfrngz/hD/hL4/e4v01PVNQ0
q5a5uYbRbWIKkEoRI4gzbVG9/wCI/erSFSLv0IlCSaPTKKKK4DtCiiigAooooA5fUf8AkqHh/wD7
A+pf+j7Guorl9R/5Kh4f/wCwPqX/AKPsa6iqeyIW7CiiipLCiiigArF+F/8AyK9z/wBhjVv/AE43
FbVYvwv/AORXuf8AsMat/wCnG4r0cF8TPPxfwo62iiivXPMCiiigAooooAKKKKACiiigAooooA4u
L/kqmv8A/YF03/0ff10Nc9F/yVTX/wDsC6b/AOj7+uhrwcV/Gl/XQ9rD/wAJBXhvjS3uIvi14l1i
yRpb3R9E0++jjT70oW5nLR/Rh/KvcqYLeISSyeVH5kqhHfYNzKCSAT6cnj3rKnP2bua1I86seG+D
1OpfEzwf4omDef4jn1S8g3gg/Y1tWS2OCMjdGqMR6k1zXizxFbX3ja01O1tdO06/XxVBpDNJdyvq
E0ZulhkJhC7UjZScEnkH1r6XW3hV4HWGINAnlxEIP3a424XjgY44qFdLsVuDcfYLQ3BYOZjboXLA
5B3YzkEA10KtG6bWiOd0ZWaueAfC/S7fw63wXu7VX+267DPBf3EkjM0yi0uJQDk44aJayNMh0L+x
fHmpavKp8XW/iTUo9FhlnZZAoumMYhQH5t0jOCcHpzivptLWCM2xS3hX7MCINsajygQQdvHHBI49
TXJ/DvTrOXR7i5ks7aW5TWdV2TSQqzr/AMTC46MRkfhT9tF3dheyasrnkPgCG4m8YX8Xinfa+H01
+WaNYnOyXUTZ2ZKTnjaBk7eoJLZxgZueINP1CbVtY8LW88kH2DUZPECSIxyLcJEUDc/daQ3Ix/sV
78bWBlZTbwlWl85lMakGTAG48cnAHPtS+REZppTDGZZkEckmwbmUEkKTjpyePc0nXi5XsNUWla58
+X2pWWr6VbX1/Y2d2njHVLu7ik1q8e2tILeBViiJZQTlkjVlXHJY1Q+A+mWnjDxXHLqm3ULfT9Nu
BbRq0iw/utTljiYA4PCquMjPHNfRs2m2dzBBBNZW0sEAAihkgRkQDphSMCpIbWC1yYLeCAsCCYol
Q4LbiOB/eJP1p+3jZpIPYyum2cJ8E5TceF9ZkYksfEOpjkk4AuGAHPYCr/xY/wCRPX/sKaZ/6XwV
10MMdvH5cUaRJuZ9sahRuJyTx3Jrkfix/wAiev8A2FNM/wDS+CsYS5q0Wu6NZLlpNPszPooor6U8
MKP50Vb03T5NSulhT5T3agCpR9Bmuz/4Q208oKJJBIP4uMflXPaxosukyLuIeJjhXFK6AzfA3/JQ
PEn/AGC9O/8ARt7XoFef+B/+SgeJP+wZp3/o29r0CvnsV/Gl/XQ9rD/wkFFFFch0hRRRQAVy/wAK
/wDkl/g//sD2f/ohK6iuX+Ff/JL/AAf/ANgez/8ARCVX2WR9pHUUUUVJYUUUUAFcv4w/5GHwP/2G
JP8A033ldRXL+MP+Rh8D/wDYYk/9N95VR3IlsdRRRRUlhRRRQAUUUUAeX2//ACOHjX/sKRf+kFpW
hWfb/wDI4eNf+wpF/wCkFpWhX09H+FH0R4FT45eoUUUVsZhRRRQAUUUUAFFFFABRRRQAUUUUAFFF
FABRRRQAUUUUAFFFFABRRRQAUUUUAFFFFABRRRQAUUUUAFFFFABRRRQAUUUUAFFFFABRRRQAUUUU
AFFFFABRRRQAUUUUAFFFFABRRRQAUUUUAFFFFABRRRQAUUUUAFFFFABRRRQAUUUUAFFFFAGLrlnN
qHiLwfBBfXGmyvqkmLq1WNpExY3R4EiOvOMcqeCeh5rsv+EP1b/oeNe/78af/wDItcvcf8jh4K/7
Ckv/AKQXdeoV4mNk1UXoephVeD9Tl/8AhD9W/wCh417/AL8af/8AItH/AAh+rf8AQ8a9/wB+NP8A
/kWuoorg5mdvKjl/+EP1b/oeNe/78af/APItH/CH6t/0PGvf9+NP/wDkWuooo5mHKjl/+EP1b/oe
Ne/78af/APItc34V8K6nJrvjFV8Y63CY9VjVnSGxzKfsNodzZtiM4IX5QBhRxnJPplcv4P8A+Rh8
cf8AYYj/APTfZ1UZOzJcVdB/wh+rf9Dxr3/fjT//AJFo/wCEP1b/AKHjXv8Avxp//wAi11FFTzMr
lRy//CH6t/0PGvf9+NP/APkWj/hD9W/6HjXv+/Gn/wDyLXUUUczDlRy//CH6t/0PGvf9+NP/APkW
ub+JXhXU7f4c+KpZPGOt3UcelXTNBLDYhJAIWJVttsGwehwQeeCK9Mrl/ip/yS/xh/2B7z/0Q9VG
T5kTKK5WH/CH6t/0PGvf9+NP/wDkWj/hD9W/6HjXv+/Gn/8AyLXUUVPMyuVHL/8ACH6t/wBDxr3/
AH40/wD+RaP+EP1b/oeNe/78af8A/ItdRRRzMOVHL/8ACH6t/wBDxr3/AH40/wD+RaP+EP1b/oeN
e/78af8A/ItdRRRzMOVHmd94V1NfiNocR8Y620jaVqDCcw2O9AJrMFR/o23B3AnIJ+UYI5z0n/CH
6t/0PGvf9+NP/wDkWjUf+SoeH/8AsD6l/wCj7GuoqnJ2RCirs5f/AIQ/Vv8AoeNe/wC/Gn//ACLR
/wAIfq3/AEPGvf8AfjT/AP5FrqKKnmZfKjl/+EP1b/oeNe/78af/APItH/CH6t/0PGvf9+NP/wDk
Wuooo5mHKjl/+EP1b/oeNe/78af/APItc/8AD7w5q0mg3Ji8Z63bKNV1NdkcFiQSL6cFvmticsQW
POMk4AGAPSK5f4b/APIvXf8A2GNV/wDThcVpGpKKbi7GcqcZNJkn/CMa1/0Pevf+A+nf/IlH/CMa
1/0Pevf+A+nf/IldJRT9vV/mF7Gn/Kc3/wAIxrX/AEPevf8AgPp3/wAiUf8ACMa1/wBD3r3/AID6
d/8AIldJRR7er/MHsaf8pzf/AAjGtf8AQ969/wCA+nf/ACJWbr1vr3hqCwvU8Y6veg6nYW7291b2
PlyRy3cMTqdlurD5XbkMCDiu2rmfiH/yA7H/ALDWk/8Apwt60p1qjnFOXUipRpqDaXQ7miiivcPG
CiiigAooooA5fWvA76p4gl1i01/VNGuZrWK0lWxW2ZHSN5WQkTQyEEGZ+hHb0qv/AMIHqf8A0PXi
D/vzp/8A8iV2FFZunCTu0i1UnFWTOP8A+ED1P/oevEH/AH50/wD+RKP+ED1P/oevEH/fnT//AJEr
sKKXsqf8q+4ftJ/zM4//AIQPU/8AoevEH/fnT/8A5Eo/4QPU/wDoevEH/fnT/wD5ErsKKPZU/wCV
fcHtJ/zM4/8A4QPU/wDoevEGO/7nT/8A5EqjbfDG90WwnisPG2vQqZZrnDRWDAySSNJIebXPLux9
BnA4rvqRlDqVPQjFP2VP+VfcHtJ/zM8ea28QqxH/AAmuscHH/HvYf/I1J9n8Q/8AQ66x/wCA9h/8
jV0niHTBpt8QufLf5lrLq/Y0v5V9we0n/MzP+z+If+h11j/wHsP/AJGo+z+If+h11j/wHsP/AJGr
Qoo9jS/lX3B7Sf8AMzP+z+If+h11j/wHsP8A5GqvfaLqerRxQ6j4p1a/tUnhuDbyRWaK7RSLIgJS
BWxuRehFbFFNUaad1FfcHtJvRthRRRWpmLW54Rlij1Bg5wxHyVhUqOYWVgcMvIIoA9SrB12EapqF
rp5faDl2I69DV/R9SXUrJJGYb8fMFyMGk1C6ttOjnvDs87bjg8n0FZ9QPK73Q7u3166v9O13UNJm
mhjtpVtUt3WRY2kZCfNicggyv0I6il+z+If+h11j/wAB7D/5GrTlkMsju33mOTTKHShJ3cUWqk4q
yZn/AGfxD/0Ousf+A9h/8jUfZ/EP/Q66x/4D2H/yNWhRU+xpfyr7h+0n/MzP+z+If+h11j/wHsP/
AJGo+z+If+h11j/wHsP/AJGrQoo9jS/lX3B7Sf8AMzP+z+If+h11j/wHsP8A5GqT4a+FdTuPhz4V
lj8Y63axyaVassEUNiUjBhUhV3WxbA6DJJ45Jq5Wx8K/+SX+D/8AsD2f/ohK8/GRjTiuVJfI7MNJ
zk+Zh/wh+rf9Dxr3/fjT/wD5Fo/4Q/Vv+h417/vxp/8A8i11FFeXzM9HlRy//CH6t/0PGvf9+NP/
APkWj/hD9W/6HjXv+/Gn/wDyLXUUUczDlRy//CH6t/0PGvf9+NP/APkWub8VeFdTj13wcreMdbmM
mqyKrvDY5iP2G7O5cWwGcAr8wIwx4zgjo/iF40n8E6ZYTWulnV7y+1C306C188QAyTSrGpLkEAZY
dq5O+8aXuta54WgudIj0/VtP8RC3ubNr1XRBJY3eGEm0A/LlsY5xjvWsVNrmtp8jKTiny31+Z1v/
AAh+rf8AQ8a9/wB+NP8A/kWj/hD9W/6HjXv+/Gn/APyLXRzXlvbSKks8UTN91XcAn6ZrC8JeM4fF
UOry+T9jTT9Tl0zMkgPmsiRtuHpnzBx7VneT1t+BdlsQ/wDCH6t/0PGvf9+NP/8AkWj/AIQ/Vv8A
oeNe/wC/Gn//ACLXUUUuZlcqOX/4Q/Vv+h417/vxp/8A8i0f8Ifq3/Q8a9/340//AORa6iijmYcq
PJdDs5tP8ReMIJ7641KVNUjzdXSxrI+bG1PIjRF4zjhRwB1PNbVZ9v8A8jh41/7CkX/pBaVoV9LR
/hx9EeFU+OXqFFFFamYUUUUAFFFFABRRRQAUUUUAFFFFABRRRQAUUUUAFFFFABRRRQAUUUUAFFFF
ABRRRQAUUUUAFFFFABRRRQAUUUUAFFFFABRRRQAUUUUAFFFFABRRRQAUUUUAFFFFABRRRQAUUUUA
FFFFABRRRQAUUUUAFFFFABRRRQAUUUUAFFFFABRRRQBn3H/I4eCv+wpL/wCkF3XqFeX3H/I4eCv+
wpL/AOkF3XqFeHjv4q9D1sJ8D9QooorzjtCiiigArl/B/wDyMPjj/sMR/wDpvs66iuX8H/8AIw+O
P+wxH/6b7OrjsyXujqKKKKgoKKKKACuX+Kn/ACS/xh/2B7z/ANEPXUVy/wAVP+SX+MP+wPef+iHq
4fEiZfCzqKKKKgoKKKKACiiigDl9R/5Kh4f/AOwPqX/o+xrqK5fUf+SoeH/+wPqX/o+xrqKp7Ihb
sKKKKksKKKKACuX+G/8AyL13/wBhjVf/AE4XFdRXL/Df/kXrv/sMar/6cLiq+yyPtI6iiiipLCii
igArmfiH/wAgOx/7DWk/+nC3rpq5n4h/8gOx/wCw1pP/AKcLetaX8SPqjKp8EvQ7miiivozwQooo
oAKKKKACiiigAooooAKKKKACiiigCnqmlw6pb+XIMMOVfuK4XUtJuNMkxKh2n7rdiK9GqjrFkb/T
5YgMtjK+xqkwPOqKdJG0cjI67WU4xTasAooooAKKKKACiiigCSK4lhOY5GQ/7JIpru0jZdix9WOa
bRQAUUUUAFFFFABRRRQAVsfCv/kl/g//ALA9n/6ISsetj4V/8kv8H/8AYHs//RCV5eP+GJ34T4md
RRRRXjHqBRRRQB5V+0NcpZ+H/DVxJqQ0aKLxJpjtqDBSLYC6jJkO8Ffl68jHFeReLTa69NoKaLrQ
8Xabb+MtI1O98QOqfv5jcrEIAUAQ4EpIAHAU19ZjhgR1ByK5rxjcSnxB4GBkbA1mQjn/AKh94a7K
NZQVmu5yVqTk7pnjP7QGuafNrXie0vLHQ7a903Tln0+61K0M97PIQzf6IDnbsKDcQMjIqp8N7Pd4
ia+8TRm48MprUrWceP3K37WtqQ86nrxu2dgS3civpdZGQkg4LdT60pmdiCWJIOR9fWnGuow5bClR
blzXG9eaSlZixJJyTSVxHYFFFFAHl9v/AMjh41/7CkX/AKQWlaFZ9v8A8jh41/7CkX/pBaVoV9PR
/hR9EeBU+OXqFFFFbGYUUUUAFFFFABRRRQAUUUUAFFFFABRRRQAUUUUAFFFFABRRRQAUUUUAFFFF
ABRRRQAUUUUAFFFFABRRRQAUUUUAFFFFABRRRQAUUUUAFFFFABRRRQAUUUUAFFFFABRRRQAUUUUA
FFFFABRRRQAUUUUAFFFFABRRRQAUUUUAFFFFABRRRQBi65eTaf4i8HzwWNxqUqapJi1tWjWR82N0
ODI6LxnPLDgHqeK7L/hMNW/6EfXv+/8Ap/8A8lVy9x/yOHgr/sKS/wDpBd16hXiY1r2i06HqYVe4
9epy/wDwmGrf9CPr3/f/AE//AOSqP+Ew1b/oR9e/7/6f/wDJVdRRXBzLsdtn3OX/AOEw1b/oR9e/
7/6f/wDJVH/CYat/0I+vf9/9P/8Akquooo5l2Cz7nL/8Jhq3/Qj69/3/ANP/APkqub8K+KtTj13x
iy+DtbmMmqxsyJNY5iP2G0G1s3IGcAN8pIww5zkD0yuX8H/8jD44/wCwxH/6b7Oqi1Z6EtO61D/h
MNW/6EfXv+/+n/8AyVR/wmGrf9CPr3/f/T//AJKrqKKnmXYqz7nL/wDCYat/0I+vf9/9P/8Akqj/
AITDVv8AoR9e/wC/+n//ACVXUUUcy7BZ9zl/+Ew1b/oR9e/7/wCn/wDyVXN/ErxVqdx8OfFUUng7
W7WOTSrpWnlmsSkYMLAswW5LYHU4BPHANemVy/xU/wCSX+MP+wPef+iHqotcy0JknyvUP+Ew1b/o
R9e/7/6f/wDJVH/CYat/0I+vf9/9P/8AkquooqeZdirPucv/AMJhq3/Qj69/3/0//wCSqP8AhMNW
/wChH17/AL/6f/8AJVdRRRzLsFn3OX/4TDVv+hH17/v/AKf/APJVH/CYat/0I+vf9/8AT/8A5Krq
KKOZdgs+55nfeKtTb4jaHKfB2trIulagogM1jvcGazJYH7TtwNoByQfmGAecdJ/wmGrf9CPr3/f/
AE//AOSqNR/5Kh4f/wCwPqX/AKPsa6iqbVloQk7vU5f/AITDVv8AoR9e/wC/+n//ACVR/wAJhq3/
AEI+vf8Af/T/AP5KrqKKnmXYuz7nL/8ACYat/wBCPr3/AH/0/wD+SqP+Ew1b/oR9e/7/AOn/APyV
XUUUcy7BZ9zl/wDhMNW/6EfXv+/+n/8AyVXN+APFWpwaFdKng7W7gHVdSbfHNYgAm+nJX5rkHKkl
TxjIOCRgn0yuX+G//IvXf/YY1X/04XFVdcr0Is+Zah/wmGrf9CPr3/f/AE//AOSqP+Ew1b/oR9e/
7/6f/wDJVdRRU8y7F2fc5f8A4TDVv+hH17/v/p//AMlUf8Jhq3/Qj69/3/0//wCSq6iijmXYLPuc
v/wmGrf9CPr3/f8A0/8A+Sq53x54s1OXRbMSeDdbt1XVtMffJNYkErfQEL8tyTliAo7ZIyQMkelV
y/xI/wCRetP+wxpX/pwt6uErTTsRON4tXLX/AAnmq7v+RE1/b6+fp+f/AEqpf+E81TP/ACIviDGP
+e+n/wDyVW7RXT9cqdkc/wBUh3Zhf8J5qm7/AJEXxBtx/wA99Pz/AOlVH/Cean/0I3iD/v8Aaf8A
/JdbtFH1yp2QfVId2YX/AAnmp/8AQjeIP+/2n/8AyXR/wnmp/wDQi+IP+/2n/wDyXW7RR9cqdkH1
SHdnMR/E+6m1S405PBXiA3lvDHcSR+ZYfLHI0ioc/asHJik4ByNvPUZtf8J5qf8A0IviD/v9p/8A
8l1U07/kqHiD/sD6b/6Pvq6iqljKieyJWFg+rML/AITzU/8AoRfEH/f7T/8A5Lo/4TzU/wDoRfEH
/f7T/wD5LrdoqfrlTsivqkO7ML/hPNT/AOhF8Qf9/tP/APkuj/hPNT/6EXxB/wB/tP8A/kut2ij6
5U7IPqkO7ML/AITzU/8AoRfEH/f7T/8A5Lra8LeIovFWjJqEVrcWQM09u9vdbPMjkileJwdjMv3k
bkMRjFPrF+F//Ir3P/YY1b/043FdeHryrNqRy16MaSTR1tFFRXUwt7aSU9EGa7jjOU8WaeqXBuEd
AWGGjzzXOVNdXMl5cPNIdzMx71DWqAKKKKACiiigAooooAKKKKACiiigAooooAKKP/10UAFZvgrx
rfeG/Bug6Tc+ENbe5sLC3tZWilsihZI1UlSbkHGRxkCtKisatGNZJSNadSVN3iWP+FnT/wDQna9/
38sf/kmj/hZ0/wD0J2vf9/LH/wCSar0Vz/UqRt9aqFj/AIWdP/0J2vf9/LH/AOSaP+FnT/8AQna9
/wB/LH/5JqvRR9SpB9aqFj/hZ0//AEJ2vf8Afyx/+Saxde8a32qap4cuYvCGtrHpt+91MHlsgWU2
txDhf9J5O6VTzjgH6HSoprB0kL6zUZY/4WdP/wBCdr3/AH8sf/kmj/hZ0/8A0J2vf9/LH/5JqvRS
+pUh/WqhY/4WdP8A9Cdr3/fyx/8Akmj/AIWdP/0J2vf9/LH/AOSar0UfUqQfWqhY/wCFnT/9Cdr3
/fyx/wDkmj/hZ0//AEJ2vf8Afyx/+Sar0UfUqQfWqhk6LJc3ureI9SuNPuNMW/v0mhgumiaTYtrB
Fk+W7qPmjbv0xWtRRXZGKilFdDlk3JtsKKKKoQUUUUAU9a1SLQ9HvtSnV3gs4JLiRYwCxVFLEDJA
zgetR/aPEP8A0JWsf+BFh/8AJNZ/xE/5J/4m/wCwXdf+imr2CuHFV5UbcvU66FGNW/N0PL/tHiH/
AKErWP8AwIsP/kmj7R4h/wChK1j/AMCLD/5Jr1CiuH69V7I6/qkO7PL/ALR4h/6ErWP/AAIsP/km
j7R4h/6ErWP/AAIsP/kmvUKKPr1Xsg+qQ7s8v+0eIf8AoStY/wDAiw/+Saqya5q8OqW+nP4P1gXl
xDJcRx+dY/NHG0auc/acDBlj4Jyd3HQ49arl9R/5Kh4f/wCwPqX/AKPsaaxtR9ES8LBdWcv9o8Q/
9CVrH/gRYf8AyTR9o8Q/9CVrH/gRYf8AyTXqFFL69V7Ir6pDuzy/7R4h/wChK1j/AMCLD/5Jo+0e
If8AoStY/wDAiw/+Sa9Qoo+vVeyD6pDuzy/7R4h/6ErWP/Aiw/8Akmj7R4h/6ErWP/Aiw/8AkmvU
KKPr1Xsg+qQ7s8ls9c1fULi+gg8H6xJLYzC3uF86xGyQxpIBzc8/JIhyMjnHUGrX2jxD/wBCVrH/
AIEWH/yTXUeD/wDkYfHH/YYj/wDTfZ11FOWNqJ7IlYWD6s8v+0eIf+hK1j/wIsP/AJJo+0eIf+hK
1j/wIsP/AJJr1Cil9eq9kV9Uh3Z5f9o8Q/8AQlax/wCBFh/8k0faPEP/AEJWsf8AgRYf/JNeoUUf
XqvZB9Uh3Z5Lquuavoml3mo3vg/WIbOzhe4nk86xbZGilmOBcknAB4AzW1Wx8VP+SX+MP+wPef8A
oh6x69DC1pVk3I469JUmkgooorsOUKKKKACiiigAooooAKKKKACiiigAooooAKKKKACiiigAoooo
AKKKKACiiigAooooAKKKKACiiigAooooAKKKKACiiigAooooAKKKKACiiigDPuP+Rw8Ff9hSX/0g
u69Qry+4/wCRw8Ff9hSX/wBILuvUK8PHfxV6HrYT4H6hRRRXnHaFFFFABXL+D/8AkYfHH/YYj/8A
TfZ11Fcv4P8A+Rh8cf8AYYj/APTfZ1cdmS90dRRRRUFBRRRQAVy/xU/5Jf4w/wCwPef+iHrqK5f4
qf8AJL/GH/YHvP8A0Q9XD4kTL4WdRRRRUFBRRRQAUUUUAcvqP/JUPD//AGB9S/8AR9jXUVy+o/8A
JUPD/wD2B9S/9H2NdRVPZELdhRRRUlhRRRQAVy/w3/5F67/7DGq/+nC4rqK5f4b/APIvXf8A2GNV
/wDThcVX2WR9pHUUUUVJYUUUUAFcv8SP+RetP+wxpX/pwt66iuX+JH/IvWn/AGGNK/8AThb1cPiR
MvhZ1FFFFQUFFFFABRRRQBy+nf8AJUPEH/YH03/0ffV1Fcvp3/JUPEH/AGB9N/8AR99XUVct/uJj
sFFFFQUFFFFABWL8L/8AkV7n/sMat/6cbitqsX4X/wDIr3P/AGGNW/8ATjcV6OC+Jnn4v4UdbWb4
iRn0e4KnBXk+9aVYHifVoobV7UNvmcYKjsK9hHmHGe1JS0laAFFFFABRRRQAUUUUAFFFFABVzTdP
OoTMolSIKM7nNU6UHtQBvf8ACIXLf6uWNkPRhyPeqjeH7nziihWXeI93IGcVWt9Wu7WMJFOyJnhe
1PbW76TO64YknPb8+lLUB9/od1p6lpVXYo++G61nVNNeT3P+tlaT2ZqhpgFFFFABRRRQAUUUUAFF
FFABRRRQAUUUUAFFFFABRRRQAUUUUAFFFFAHP/ET/kn/AIm/7Bd1/wCimr2CvH/iJ/yT/wATf9gu
6/8ARTV7BXkY/wCz8/0PRwf2vkFFFFeSekFFFFABXL6j/wAlQ8P/APYH1L/0fY11FcvqP/JUPD//
AGB9S/8AR9jVR3IlsdRRRRUlhRRRQAUUUUAcv4P/AORh8cf9hiP/ANN9nXUVy/g//kYfHH/YYj/9
N9nXUVct/uJjsFFFFQUFFFFAHL/FT/kl/jD/ALA95/6Iesetj4qf8kv8Yf8AYHvP/RD1j17OA+GR
5eL+JBRRRXqHAFFFFABRRRQAUUUUAFFFFABRRRQAUUUUAFFFFABRRRQAUUUUAFFFFABRRRQAUUUU
AFFFFABRRRQAUUUUAFFFFABRRRQAUUUUAFFX5dDvoY97W749hV7SfDLX8e+V2g2nlSvP5nii6Awq
K7C+0fTdH02VnXzGPCsTk5rj/pQBn3H/ACOHgr/sKS/+kF3XqFeY6tottrS2wuDcI1vL50Mtrcy2
8iPsZMh42Vh8rsOvQmqv/CLQf9BLXv8Awf33/wAerz8RhpVp8yZ2Ua6pRs0esUV5P/wi0H/QS17/
AMH99/8AHqP+EWg/6CWvf+D++/8Aj1c31Cf8x0fW49j1iivJ/wDhFoP+glr3/g/vv/j1H/CLQf8A
QS17/wAH99/8eo+oT/mD63HsesVy/g//AJGHxx/2GI//AE32dcf/AMItB/0Ete/8H99/8eqKHwXY
28k8kV5rcUk7+ZMya7egyMFVdzHzuTtVRk9lA7U1gZK+pLxcdND12ivJ/wDhFoP+glr3/g/vv/j1
H/CLQf8AQS17/wAH99/8epfUJ/zFfW49j1iivJ/+EWg/6CWvf+D++/8Aj1H/AAi0H/QS17/wf33/
AMeo+oT/AJg+tx7HrFcv8VP+SX+MP+wPef8Aoh64/wD4RaD/AKCWvf8Ag/vv/j1RXXguxvrWa2ub
zW7i2mRo5YZddvWR1IwVYGbBBBwQaccDJNO5LxcWrWPXaK8n/wCEWg/6CWvf+D++/wDj1H/CLQf9
BLXv/B/ff/HqX1Cf8xX1uPY9Yoryf/hFoP8AoJa9/wCD++/+PUf8ItB/0Ete/wDB/ff/AB6j6hP+
YPrcex6xRXk3/CLwf9BLXv8Awf33/wAeroLTwz4cWyja4vfEBn7hfEOof0npfUZ9w+tx7GjqP/JU
PD//AGB9S/8AR9jXUV5KvhXStQ+Jml28c2tLbf2VfOGOvX5kyJrMDDGbcB8xyAQDxkHaMdl/wrfS
f+fvXv8AwotQ/wDj9ctWmqcuSTN6c3UTkkdRRXL/APCt9J/5+9e/8KLUP/j9H/Ct9J/5+9e/8KLU
P/j9Y+73Nve7HUUVy/8AwrfSf+fvXv8AwotQ/wDj9H/Ct9J/5+9e/wDCi1D/AOP0e73D3ux1Fcv8
N/8AkXrv/sMar/6cLij/AIVvpP8Az969/wCFFqH/AMfrm/AHgDTLrQrp3utbUjVdSj/d69fRjC30
6jhZgM4AyepOSSSSar3eV6ke9zLQ9Morl/8AhW+k/wDP3r3/AIUWof8Ax+j/AIVvpP8Az969/wCF
FqH/AMfqfd7l+92Ooorl/wDhW+k/8/evf+FFqH/x+j/hW+k/8/evf+FFqH/x+j3e4e92Oorl/iR/
yL1p/wBhjSv/AE4W9H/Ct9J/5+9e/wDCi1D/AOP1zfj/AMAaZa6Faul1rbE6rpsf7zXr6QYa+gU8
NMRnBOD1BwQQQDVR5eZaky5uV6HplFcv/wAK30n/AJ+9e/8ACi1D/wCP0f8ACt9J/wCfvXv/AAot
Q/8Aj9T7vcr3ux1FFcv/AMK30n/n717/AMKLUP8A4/R/wrfSf+fvXv8AwotQ/wDj9Hu9w97sdRRX
L/8ACt9J/wCfvXv/AAotQ/8Aj9H/AArfSf8An717/wAKLUP/AI/R7vcPe7Bp3/JUPEH/AGB9N/8A
R99XUV5nY+ANMb4ja5bm61vy49K0+QMNevg+WmvAcv524j5RgE4GTgDcc9J/wrfSf+fvXv8AwotQ
/wDj9VLlvuTHmtsdRRXL/wDCt9J/5+9e/wDCi1D/AOP0f8K30n/n717/AMKLUP8A4/U+73K97sdR
RXL/APCt9J/5+9e/8KLUP/j9H/Ct9J/5+9e/8KLUP/j9Hu9w97sdRWJ8L8f8IvdZ4H9sat/6cbiq
X/Ct9J/5+9e/8KLUP/j9c78P/AmnXOg3TNea4hGq6nHiLX76MYW+nUcLMBnAGT1JySSSTXVh6kKL
cmctanKrZI9D1nxFb2tvIkMoafoMdq4iSRpGLOcu3JPrV9vhToEjEs+tMT1J1+/P/tak/wCFT+H/
AO9rP/g+v/8A49XcsdTXRnL9Un3Rn0Vof8Kn8Pf3tY/8H1//APHqP+FT+Hv72sf+D6//APj1P69T
7MPqk+6M+itD/hU/h7+9rH/g+v8A/wCPVz3jrwLpnhnQ4dR06bVorqPUbBA0msXkqlXvIUcFHlKs
CrMMEHrVRxtOUlFJ6kyws4pttGjRRRXecgUUUUAFFFFABRRRQAUUUUAFKp2sOMkdj0pKWgDq9Gsd
O1iz2vAFmX7+0kVabwhYsVw0if8AAv8AGuSsdQn02RmgYIzdcjOank1y9dVHmuu1tw2nv7+1KzA2
5vBIZ8w3G1fRxmon8EyblCTrjHzMVJ5/OoLfxhdxoRMokPGDgCrU/jTKKIIMN/EXP8qPeAjbwTMq
ki5QnsNh/wAay7jQb62kVHgO5jwRyDXa6bq8Goxq0bjfjLKO1XP4Qe36UrsDg5PDOoRqGMIYdflO
TVX+ybzbn7NJgf7Nej0fSlzAeaRWFzLnZA7Y/wBmlaxuV6wSD8K9Kop8wHmM1vLb48yNkDcrkVFX
ptzaw3ahZo1kA6bgDisfUPCdrOhMH7h+3PFPmA4qitm68K30DYRPOX+8lS2vhC7mh3yssJ7Bu9O6
AwaKqaD4Es9c17xYNWm1GSWz1NLeJbbVbqCNI/sdtJgLHIq/ekY5xnmtv/hU/h7+9rH/AIPr/wD+
PVwzxkIScWnodccNOcVJNGfRWh/wqfw9/e1j/wAH1/8A/HqP+FT+Hv72sf8Ag+v/AP49UfXqfZlf
VJ90Z9FaH/Cp/D397WP/AAfX/wD8eo/4VP4e/vax/wCD6/8A/j1H16n2YfVJ90cf8RP+Sf8Aib/s
F3X/AKKavYK8s+JHwx0PT/h34puoW1bzYdKupE8zWr2RdwhYjKtMVYZHQgg966v/AIVvpP8Az969
/wCFFqH/AMfrjxNaFZRaut/0OmhTlSbTOoorl/8AhW+k/wDP3r3/AIUWof8Ax+j/AIVvpP8Az969
/wCFFqH/AMfri93udfvdjqKK5f8A4VvpP/P3r3/hRah/8fo/4VvpP/P3r3/hRah/8fo93uHvdjqK
5fUf+SoeH/8AsD6l/wCj7Gj/AIVvpP8Az969/wCFFqH/AMfrm77wBpi/EbQ7cXWt+XJpWoSFjr18
Xys1mBh/O3AfMcgHBwMg7Rio8t9yJc1tj0yiuX/4VvpP/P3r3/hRah/8fo/4VvpP/P3r3/hRah/8
fqfd7l+92Ooorl/+Fb6T/wA/evf+FFqH/wAfo/4VvpP/AD969/4UWof/AB+j3e4e92Ooorl/+Fb6
T/z969/4UWof/H6P+Fb6T/z969/4UWof/H6Pd7h73YPB/wDyMPjj/sMR/wDpvs66ivM/CvgDTJ9d
8Yo11rYEOqxxrs16+UkfYbRvmImyxyx5bJxgZwAB0n/Ct9J/5+9e/wDCi1D/AOP1UuW+5Mea2x1F
Fcv/AMK30n/n717/AMKLUP8A4/R/wrfSf+fvXv8AwotQ/wDj9T7vcr3ux1FFcv8A8K30n/n717/w
otQ/+P0f8K30n/n717/wotQ/+P0e73D3uwfFT/kl/jD/ALA95/6IeseqfxK8AaZZ/DnxVcR3WttJ
FpV1Iqy69fSISIWI3I0xVh6ggg9xW5/wqfw9/e1j/wAH1/8A/Hq78PXhQi73dzjrUp1WrdDPorQ/
4VP4e/vax/4Pr/8A+PUf8Kn8Pf3tY/8AB9f/APx6ur69T7M5/qk+6M+itD/hU/h7+9rH/g+v/wD4
9R/wqfw9/e1j/wAH1/8A/HqPr1Psw+qT7oz6K0P+FT+Hv72sf+D6/wD/AI9XNat4btPCvjjRoNPm
v/IutOvXmiutRuLlWZJbUIQJXYAgSPyMfeNaU8XCpJQSepE8POnHmbNWiiiu05QooooAKKKKACii
igAooooAKKKKACiiigAooooAKKKKACiiigAooooAKKKKACiiigAooooAKKKKACiiigD1P680dKKK
yAhu7WK+hMUyh1P8P+FcZ4h0JNK2SwsWhfjB7H0rueO5xWD4q1CK3tfIcZkbkA/zqkBxXpRR39Di
irAKKKKACiiigAooooAKKKKACiiigAooooAKKKKACiiigA9auabps2pziOJcqD87dgKp1e0vV5tJ
kdo+QwwQaALF1psWl/Efw3DEOP7H1MlvX9/YV1VczqN0t58SPDEyZw2i6kef+u9jXTV8/i/4p7GF
/hhRRRXEdYUUUUAFcv8ADf8A5F67/wCwxqv/AKcLiuorl/hv/wAi9d/9hjVf/ThcVX2WR9pHUUUU
VJYUUUUAFcv8SP8AkXrT/sMaV/6cLeuorl/iR/yL1p/2GNK/9OFvVw+JEy+FnUUUUVBQUUUUAFFF
FAHL6d/yVDxB/wBgfTf/AEffV1Fcvp3/ACVDxB/2B9N/9H31dRVy3+4mOwUUUVBQUUUUAFcv8N/+
Reu/+wxqv/pwuK6iuX+G/wDyL13/ANhjVf8A04XFV9lkfaR1FFFFSWFFFFABXH/Fj/kT1/7Cmmf+
l8FdhXH/ABY/5E9f+wppn/pfBWtH+JH1RlU+CXoZ9FFFfUHghRRRQAUUUUAFFFFABRRRQAUUUUAF
FFFABRRRQBIlxJHG6K7Kj/eAPWrlrrNza24hVsIB64Oaz6OaAOt07xapmjSc4VlwzY4Df/XrpIZE
njEkbBkboy8ivL+asW+o3Vqu2Gd419FPFS0B6VRXH2vjKaKDbJCJZB0bdjNaFr4ytZWAlR4RjJYj
IqbMDoKOnTiqlhq1tqW7yJN23qCMGlvNUtbAgTzKpJwAOaQFr+dHfI4NU7XWLS8jDxTLgnGGODmr
KTRyLuV1Zf7wYYoA4vwx/wAjR47/AOwxF/6brOukrmvCsiyeJfHTIQynWI8EHP8AzD7Oulr5/Efx
ZHuUf4cQooornNwooooA5f4qf8kv8Yf9ge8/9EPXUVy/xU/5Jf4w/wCwPef+iHrqKv7K/rsT9phR
RRUFBRRRQAVy+o/8lQ8P/wDYH1L/ANH2NdRXL6j/AMlQ8P8A/YH1L/0fY1UdyJbHUUUUVJYUUUUA
FFFFAHL+D/8AkYfHH/YYj/8ATfZ11Fcv4P8A+Rh8cf8AYYj/APTfZ11FXLf7iY7BRRRUFBRRRQBy
/wAVP+SX+MP+wPef+iHrqK5f4qf8kv8AGH/YHvP/AEQ9dRV/ZX9diftMKKKKgoKKKKACvP8Axz/y
UDw3/wBgvUf/AEbZV6BXn/jn/koHhv8A7Beo/wDo2yrrwv8AGj/XQ5sR/CYUUUV9EeKFFFFABRRR
QAUUUUAFFFFABRRRQAUUUUAFFFFABRRRQAUUUUAFFFFABRRRQAUUUUAFFFFABRRRQAUUUUAep0et
FVNS1KLS4DLKGx229zWQDNUa88kiy2GTByGPNcNew3jEy3CSem5ga2LPxZKt026AOJH4IOGGTVjU
7pWt3gN+EEnJWVcsB7EcVeqA5P69aKdIFVmCHcueCRTaoAooooAKKKKACiiigAooooAKKKKACiii
gAooooAKKKKACjn0yO9FL/n3oA0A7t468K7k2Y0bUwPcefYV19ebXd3raeJtH1Cwgsb5bW0urMx3
129sB5r27hgyxSZx5BGMD7wrpxN43ZcjQfD5GM/8h2f/AOQ68bE0Kk6nNFaHpUK0IQtJnRUVz3m+
OP8AoAeH/wDwez//ACHR53jj/oAeH/8Awez/APyHXL9VrdvyOj6xS7nQ0Vz3m+OP+gB4f/8AB7P/
APIdHm+OP+gB4f8A/B7P/wDIdH1Wt2/IPrFLudDXL/Df/kXrv/sMar/6cLip/N8cf9ADw/8A+D2f
/wCQ65XwFfeL49Eu1g0PRJU/tbU8tJrMyHf9un3jAtDwGyAc8gA4GcBSozhH3lYcasJy91npdFcv
/aPjX/oX9B/8Hs//AMh0f2j41/6F/Qf/AAez/wDyHWPKzbmR1FFcv/aPjX/oX9B/8Hs//wAh0f2j
41/6F/Qf/B7P/wDIdHKw5kdRXL/Ej/kXrT/sMaV/6cLej+0fGv8A0L+g/wDg9n/+Q65vx/f+L20K
1FxoeiRR/wBq6aQ0eszOdwvoNgwbQcFsAnPAJODjBqMXzImUlys9Morl/wC0fGv/AEL+g/8Ag9n/
APkOj+0fGv8A0L+g/wDg9n/+Q6nlZXMjqKK5f+0fGv8A0L+g/wDg9n/+Q6P7R8a/9C/oP/g9n/8A
kOjlYcyOoorl/wC0fGv/AEL+g/8Ag9n/APkOj+0fGv8A0L+g/wDg9n/+Q6OVhzINO/5Kh4g/7A+m
/wDo++rqK8zsb/xf/wALG1xl0PRDcnStPDxnWZggXzrzaQ32TJJJfIwMYHJyQOk/tHxr/wBC/oP/
AIPZ/wD5DqpRdyYyVjqKK5f+0fGv/Qv6D/4PZ/8A5Do/tHxr/wBC/oP/AIPZ/wD5DqeVlcyOoorl
/wC0fGv/AEL+g/8Ag9n/APkOj+0fGv8A0L+g/wDg9n/+Q6OVhzI6iuX+G/8AyL13/wBhjVf/AE4X
FH9o+Nf+hf0H/wAHs/8A8h1zfgC/8XroV0LfQ9Elj/tXUiWk1mZDuN9PvGBaHgNkA55ABwM4Fcr5
WRzLmR6ZRXL/ANo+Nf8AoX9B/wDB7P8A/IdH9o+Nf+hf0H/wez//ACHU8rL5kdRRXL/2j41/6F/Q
f/B7P/8AIdH9o+Nf+hf0H/wez/8AyHRysOZHUVx/xY/5E9f+wppn/pfBVj+0fGv/AEL+g/8Ag9n/
APkOuY+It54om8OwpqOj6Ra2Z1TTfMmtdVlnkX/ToMYRrZAecD7wwCTz0OtKL9pH1RlUkuSXoX6K
KK+lPDCiiigAooooAKKKKACiiigAooooAKKKKACiiigAooooAKKKzdY1C9trrSbPTrS3u7zUbpra
Nbq4aCNcQyyliyo56REY29SKTairsaTbsjSoqv8A2L41/wCgToP/AIOZ/wD5Eo/sXxr/ANAnQf8A
wcz/APyJWH1ml/Mbexqfyl63upbbd5blNxGfwpkszzyF5GLMTmqn9i+Nf+gToP8A4OZ//kSj+xfG
v/QJ0H/wcz//ACJS+s0f5g9jU/lLIOCCOD1z705ZnT7rsO3Wqn9i+Nf+gToP/g5n/wDkSj+xfGv/
AECdB/8ABzP/APIlP6zS/mD2NT+U0Phj/wAffjHnP/E4X/0htK7ivK/Asni/T9S8XQxaNok0g1VD
Nv1iZArfYrXhf9FO4bdpycckjHGT1n9o+Nf+hf0H/wAHs/8A8h14dZc1RtbHqUnywSZ1FFcv/aPj
X/oX9B/8Hs//AMh0f2j41/6F/Qf/AAez/wDyHWPKzbmR1FFcv/aPjX/oX9B/8Hs//wAh0f2j41/6
F/Qf/B7P/wDIdHKw5kHxU/5Jf4w/7A95/wCiHrqK8z+JV/4vf4c+KludD0SG2OlXQlki1maR1XyW
yVU2ihiB0BIz6jrXSf2j41/6F/Qf/B7P/wDIdVyvlX9dieZcx1FFcv8A2j41/wChf0H/AMHs/wD8
h0f2j41/6F/Qf/B7P/8AIdTysrmR1FFcv/aPjX/oX9B/8Hs//wAh0f2j41/6F/Qf/B7P/wDIdHKw
5kdRXL6j/wAlQ8P/APYH1L/0fY0f2j41/wChf0H/AMHs/wD8h1zd9f8Ai/8A4WNobNoeiC5GlagE
jGszFCvnWe4lvsmQQQmBg5yeRgA1GLuRKSsemUVy/wDaPjX/AKF/Qf8Awez/APyHR/aPjX/oX9B/
8Hs//wAh1PKy+ZHUUVy/9o+Nf+hf0H/wez//ACHR/aPjX/oX9B/8Hs//AMh0crDmR1FFcv8A2j41
/wChf0H/AMHs/wD8h0f2j41/6F/Qf/B7P/8AIdHKw5kHg/8A5GHxx/2GI/8A032ddRXmfhW/8Xrr
vjExaHojyNqsZmV9ZmUI32G04U/ZDuG3ackDkkY4yek/tHxr/wBC/oP/AIPZ/wD5DqpRdyYyVjqK
K5f+0fGv/Qv6D/4PZ/8A5Do/tHxr/wBC/oP/AIPZ/wD5DqeVlcyOoorl/wC0fGv/AEL+g/8Ag9n/
APkOj+0fGv8A0L+g/wDg9n/+Q6OVhzIPip/yS/xh/wBge8/9EPXUV5n8Sr/xe/w58VLc6HokNsdK
uhLJFrM0jqvktkqptFDEDoCRn1HWuk/tHxr/ANC/oP8A4PZ//kOq5Xyr+uxPMuY6iiuX/tHxr/0L
+g/+D2f/AOQ6P7R8a/8AQv6D/wCD2f8A+Q6nlZXMjqKK5f8AtHxr/wBC/oP/AIPZ/wD5Do/tHxr/
ANC/oP8A4PZ//kOjlYcyOorz/wAc/wDJQPDf/YL1H/0bZVsf2j41/wChf0H/AMHs/wD8h1yPiD/h
LNS8faGkmi6LHcrpd+Y1XWZihXzbPcxb7JkEHbgYOdx5GAD0Yf3KqlLYwre9TaRrUVX/ALE8a99J
0H/wcz//ACJR/YvjX/oE6D/4OZ//AJEr2vrNL+Y8z2NT+UsUVX/sXxr/ANAnQf8Awcz/APyJR/Yv
jX/oE6D/AODmf/5Eo+s0v5g9jU/lLFFV/wCxfGv/AECdB/8ABzP/APIlH9i+Nf8AoE6D/wCDmf8A
+RKPrNL+YPY1P5SxRWPog8X69ZyXNvo+iJHHc3FqRJrEwO6GZ4XPFqeC0ZI9iOnStD+xfGv/AECd
B/8ABzP/APIlH1il/ML2NTsWKKr/ANi+Nf8AoE6D/wCDmf8A+RKP7F8a/wDQJ0H/AMHM/wD8iUfW
aX8w/Y1P5SxRVf8AsXxr/wBAnQf/AAcz/wDyJR/YvjX/AKBOg/8Ag5n/APkSj6zS/mD2NT+UsUVk
6w3ijw7axXmo6TpAs2ure2ka11WWSRfOmSIMFa2UHBcHG4cA1rVrCpGorxdzKUZQdpIKKKKskKKK
KACiiigAooooAKKKKACiiigAooooAKKKKACiiigDaj8W36qQWRyT1Zf8Ko3+qXOpY8+TcB0XFU6K
NAF9MHHvQzZOf50lFABRRRQAUUUUAFFFFABRRRQAUUUUAFFFFABRRRQAUUUUAFFFFABRRRQAtega
Lq0N/aqsfytGoUqT7V59T4Z3t5BJG7I47ik1cD0v7QskLyp8yjIP1HH9KdDJ5kKSFdpZQ22uQsfF
n2e2EUsW7DdYyFz35/OupsL6HULdXjYcrkr3WosBZooopAFcN8PP+QHff9hrVv8A04XFdzXDfDz/
AJAd9/2GtW/9OFxXBjP4a9Ttwnxv0Omooorxj1gooooAK5f4kf8AIvWn/YY0r/04W9dRXL/Ej/kX
rT/sMaV/6cLerh8SJl8LOooooqCgooooAKKKKAOX07/kqHiD/sD6b/6Pvq6iuX07/kqHiD/sD6b/
AOj76uoq5b/cTHYKKKKgoKKKKACuX+G//IvXf/YY1X/04XFdRXL/AA3/AOReu/8AsMar/wCnC4qv
ssj7SOooooqSwooooAK4/wCLH/Inr/2FNM/9L4K7CuP+LH/Inr/2FNM/9L4K1o/xI+qMqnwS9DPo
oor6g8EKKKKACiiigAooooAKKKKACiiigAooooAKKKKACiiigArPuP8AkcPBX/YUl/8ASC7rQrPu
P+Rw8Ff9hSX/ANILusa38KXozSn8cfU9Qooor5g98KKKKACiiigDl/B//Iw+OP8AsMR/+m+zrqK5
fwf/AMjD44/7DEf/AKb7Ouoq5b/cTHYKKKKgoKKKKAOX+Kn/ACS/xh/2B7z/ANEPXUVy/wAVP+SX
+MP+wPef+iHrqKv7K/rsT9phRRRUFBRRRQAVy+o/8lQ8P/8AYH1L/wBH2NdRXL6j/wAlQ8P/APYH
1L/0fY1UdyJbHUUUUVJYUUUUAFFFFAHL+D/+Rh8cf9hiP/032ddRXL+D/wDkYfHH/YYj/wDTfZ11
FXLf7iY7BRRRUFBRRRQBy/xU/wCSX+MP+wPef+iHrqK5f4qf8kv8Yf8AYHvP/RD11FX9lf12J+0w
oooqCgooooAK5fUf+SoeH/8AsD6l/wCj7Guorl9R/wCSoeH/APsD6l/6PsaqO5EtjqKKKKksKKKK
ACiiigDl/hv/AMi9d/8AYY1X/wBOFxXUVy/w3/5F67/7DGq/+nC4rqKqXxMiPwoKKKKksKKKKAOP
+LH/ACJ6/wDYU0z/ANL4Kz60Pix/yJ6/9hTTP/S+Cs+vcwP8N+p5OL+NegUUUV6JxBRRRQAUUUUA
FFFFABRRRQAUUUUAFFFFABRRRQAUUUUAFFFFABRRRQAUUUUAFFFFABRRRQAUUUUAFFFFABRRRQAU
UUUAFFFFABRRRQAUUUUAFFFFAC1b0zUpNOulkQ/L/EvqKp0UAem2d5FfW6zxHcjD/Ip808dqheVl
RR3Jrzq11S6s42jhlZEbqBUU91Nc482V5P8AeOanlA6fUPGCJlLRd5/56N0/KsX4WzNceFJZXOXf
VdUYn3N/cGsytD4T/wDInt/2FNT/APS+euDHfw16nbhPjfodhRRRXhnrBRRRQAVy/wASP+RetP8A
sMaV/wCnC3rqK5f4kf8AIvWn/YY0r/04W9XD4kTL4WdRRRRUFBRRRQAUUUUAcvp3/JUPEH/YH03/
ANH31dRXL6d/yVDxB/2B9N/9H31dRVy3+4mOwUUUVBQUUUUAFcv8N/8AkXrv/sMar/6cLiuorl/h
v/yL13/2GNV/9OFxVfZZH2kdRRRRUlhRRRQAVx/xY/5E9f8AsKaZ/wCl8FdhXH/Fj/kT1/7Cmmf+
l8Fa0f4kfVGVT4Jehn0VajtPM0+ecDlGUfnn/CqtfUHghRRRQAUUUUAFFFFABRRRQAUUUUAFFFFA
BRRRQAUUUUAFZ9x/yOHgr/sKS/8ApBd1oVn3H/I4eCv+wpL/AOkF3WNb+FL0ZpT+OPqeoUUUV8we
+FFFFABRRRQBy/g//kYfHH/YYj/9N9nXUVy/g/8A5GHxx/2GI/8A032ddRVy3+4mOwUUUVBQUUUU
Acv8VP8Akl/jD/sD3n/oh66iuX+Kn/JL/GH/AGB7z/0Q9dRV/ZX9diftMKKKKgoKKKKACuX1H/kq
Hh//ALA+pf8Ao+xrqK5fUf8AkqHh/wD7A+pf+j7GqjuRLY6iiiipLCiiigAooooA5fwf/wAjD44/
7DEf/pvs66iuX8H/APIw+OP+wxH/AOm+zrqKuW/3Ex2CiiioKCiiigDl/ip/yS/xh/2B7z/0Q9dR
XL/FT/kl/jD/ALA95/6Ieuoq/sr+uxP2mFFFFQUFFFFABXL6j/yVDw//ANgfUv8A0fY11FcvqP8A
yVDw/wD9gfUv/R9jVR3IlsdRRRRUlhRRRQAUUUUAcv8ADf8A5F67/wCwxqv/AKcLiuorl/hv/wAi
9d/9hjVf/ThcV1FVL4mRH4UFFFFSWFFFFAHH/Fj/AJE9f+wppn/pfBWfWh8WP+RPX/sKaZ/6XwVR
jjeZlVFLO3ACjNe5gf4b9TycX8a9BtFTS2s0Mjo6FWXkj8ahr0TiCiiigAooooAKKKKACiiigAoo
ooAKKKKACiiigAooooAKKKKACiiigAooooAKKKKACiiigAooooAKKKKACiiigArn/iJ/yT/xN/2C
7r/0U1dBXP8AxE/5J/4m/wCwXdf+imoA7j/hVfgr/oT9B/8ABZB/8TR/wqvwV/0J+g/+CyD/AOJr
qKK+V55dz6Hlj2OX/wCFV+Cv+hP0H/wWQf8AxNH/AAqvwV/0J+g/+CyD/wCJrqKKOeXcOWPY5f8A
4VX4K/6E/Qf/AAWQf/E0f8Kr8Ff9CfoP/gsg/wDia6iijnl3Dlj2PM774a+EU+I2h2y+FdEW2k0r
UJHhGnQ7GZZrMKxG3BIDuAe24+prpP8AhVfgr/oT9B/8FkH/AMTRqP8AyVDw/wD9gfUv/R9jXUVT
lKy1IUY3ehy//Cq/BX/Qn6D/AOCyD/4mj/hVfgr/AKE/Qf8AwWQf/E11FFTzy7l8sexy/wDwqvwV
/wBCfoP/AILIP/iaP+FV+Cv+hP0H/wAFkH/xNdRRRzy7hyx7HL/8Kr8Ff9CfoP8A4LIP/ia8x8N+
AfDE9rqBk8OaTIV1XUY1LWMRwq3kyqo+XoFAAHYACvdq8n8Lf8empf8AYY1P/wBLp69LAybk7nBi
0klYr/8ACu/Cn/Qs6P8A+AEX/wATR/wrvwr/ANCzo/8A4ARf/E10FFeweac9/wAK78Kf9Czo/wD4
ARf/ABNL/wAK78Kf9Czo/wD4ARf/ABNdBRQBz/8Awrvwp/0LGjf+AEX/AMTWT4k8BeGILXTzF4c0
mMtqunRsUsYhlWvIVZT8vQqSCO4JFdtWP4p/49NN/wCwxpn/AKXQVE/hZUfiR2H/AAqvwV/0J+g/
+CyD/wCJo/4VX4K/6E/Qf/BZB/8AE11FFfMc8u57/LHscv8A8Kr8Ff8AQn6D/wCCyD/4mj/hVfgr
/oT9B/8ABZB/8TXUUUc8u4csexy//Cq/BX/Qn6D/AOCyD/4mj/hVfgr/AKE/Qf8AwWQf/E11FFHP
LuHLHseZ2Pw18Iv8Rtctm8K6I1tHpWnyJCdOh2KzTXgZgNuASEQE99o9BXSf8Kr8Ff8AQn6D/wCC
yD/4mjTv+SoeIP8AsD6b/wCj76uoqpSlfcmMY22OX/4VX4K/6E/Qf/BZB/8AE0f8Kr8Ff9CfoP8A
4LIP/ia6iip55dyuWPY5f/hVfgr/AKE/Qf8AwWQf/E0f8Kr8Ff8AQn6D/wCCyD/4muooo55dw5Y9
jl/+FV+Cv+hP0H/wWQf/ABNY/wAOfhj4OvvDtxLc+E9DuJBqupxh5dOhYhUvp1RcleiqoUDsAAOl
egVi/C7/AJFe5/7DGrf+nC4r0MHJuTuzgxaSSsO/4VN4HH/MmeH/APwVwf8AxFYfir4ReD0tVnt/
CWiRbD83l6dCBj8Fr0f1pGVZFZWAZW6g16x5p4b/AMK78Kc/8Uzo4A/6cIv/AImj/hXfhT/oWdH/
APACL/4mvR/E+hpDElxaxcZ/ee1cz1rQDnv+Fd+FP+hZ0f8A8AIv/iauaL4B8J2+qW8x8PaVbmNw
6TR2USsjA5DAhcgg961KciGRgoGSTigDqNS0mzsdJm8qf5ZCGXd047frXK8nrya3Zobn+xTHEY5l
VhvRV+cVhlSvBGDQAlFFFABRRRQAUUUUAFFFFABRRRQAUUUUAFFFFABRRRQAVi65pVlrfiLwfZaj
Z29/Zy6pJ5lvdRLJG+LG6IyrAg4IB+oFbVZ9x/yOHgr/ALCkv/pBd1lW/hy9GaU/jj6nUf8ACq/B
X/Qn6D/4LIP/AImj/hVfgr/oT9B/8FkH/wATXUUV81zy7nu8sexy/wDwqvwV/wBCfoP/AILIP/ia
P+FV+Cv+hP0H/wAFkH/xNdRRRzy7hyx7HL/8Kr8Ff9CfoP8A4LIP/iaP+FV+Cv8AoT9B/wDBZB/8
TXUUUc8u4csex5n4V+GvhG413xjHL4V0SWODVY44VfToSI1NjaNtUFeBuZjgd2J710n/AAqvwV/0
J+g/+CyD/wCJo8H/APIw+OP+wxH/AOm+zrqKqUpX3JjGNtjl/wDhVfgr/oT9B/8ABZB/8TR/wqvw
V/0J+g/+CyD/AOJrqKKnnl3K5Y9jl/8AhVfgr/oT9B/8FkH/AMTR/wAKr8Ff9CfoP/gsg/8Aia6i
ijnl3Dlj2PM/iV8NfCNj8OfFVzbeFdEt7mHSrqSKaLToVdGELEMpC5BBGQRXSf8ACq/BX/Qn6D/4
LIP/AImj4qf8kv8AGH/YHvP/AEQ9dRVc0uVa/wBaE8sebY5f/hVfgr/oT9B/8FkH/wATR/wqvwV/
0J+g/wDgsg/+JrqKKnnl3K5Y9jl/+FV+Cv8AoT9B/wDBZB/8TR/wqvwV/wBCfoP/AILIP/ia6iij
nl3Dlj2OX/4VX4K/6E/Qf/BZB/8AE1zd98NfCKfEbQ7ZfCuiLbSaVqEjwjTodjMs1mFYjbgkB3AP
bcfU16ZXL6j/AMlQ8P8A/YH1L/0fY1UZSvuRKMbbB/wqvwV/0J+g/wDgsg/+Jo/4VX4K/wChP0H/
AMFkH/xNdRRU88u5fLHscv8A8Kr8Ff8AQn6D/wCCyD/4mj/hVfgr/oT9B/8ABZB/8TXUUUc8u4cs
exy//Cq/BX/Qn6D/AOCyD/4mj/hVfgr/AKE/Qf8AwWQf/E11FFHPLuHLHseZ+Ffhr4RuNd8Yxy+F
dEljg1WOOFX06EiNTY2jbVBXgbmY4Hdie9dJ/wAKr8Ff9CfoP/gsg/8AiaPB/wDyMPjj/sMR/wDp
vs66iqlKV9yYxjbY5f8A4VX4K/6E/Qf/AAWQf/E0f8Kr8Ff9CfoP/gsg/wDia6iip55dyuWPY5f/
AIVX4K/6E/Qf/BZB/wDE0f8ACq/BX/Qn6D/4LIP/AImuooo55dw5Y9jzP4lfDXwjY/DnxVc23hXR
Le5h0q6kimi06FXRhCxDKQuQQRkEV0n/AAqvwV/0J+g/+CyD/wCJo+Kn/JL/ABh/2B7z/wBEPXUV
XNLlWv8AWhPLHm2OX/4VX4K/6E/Qf/BZB/8AE0f8Kr8Ff9CfoP8A4LIP/ia6iip55dyuWPY5f/hV
fgr/AKE/Qf8AwWQf/E0f8Kr8Ff8AQn6D/wCCyD/4muooo55dw5Y9jl/+FV+Cv+hP0H/wWQf/ABNc
3ffDXwinxG0O2Xwroi20mlahI8I06HYzLNZhWI24JAdwD23H1NemVy+o/wDJUPD/AP2B9S/9H2NV
GUr7kSjG2wf8Kr8Ff9CfoP8A4LIP/iaP+FV+Cv8AoT9B/wDBZB/8TXUUVPPLuXyx7HL/APCq/BX/
AEJ+g/8Agsg/+Jo/4VX4K/6E/Qf/AAWQf/E11FFHPLuHLHscv/wqvwV/0J+g/wDgsg/+Jo/4VX4K
/wChP0H/AMFkH/xNdRRRzy7hyx7HmfgD4a+EbzQrqS48K6JPIuq6lGGk06FiFW+nVFyV6BVAA7AA
V0n/AAqvwV/0J+g/+CyD/wCJo+G//IvXf/YY1X/04XFdRVSlLmepEYx5Vocv/wAKr8Ff9CfoP/gs
g/8AiaP+FV+Cv+hP0H/wWQf/ABNdRRU88u5fLHscv/wqvwV/0J+g/wDgsg/+Jo/4VX4K/wChP0H/
AMFkH/xNdRRRzy7hyx7Hmfj/AOGvhGz0K1kt/CuiQSNqumxlo9OhUlWvoFdchehViCO4JFdJ/wAK
r8Ff9CfoP/gsg/8AiaPiR/yL1p/2GNK/9OFvXUVXNLlWv9aE8sebY5f/AIVX4K/6E/Qf/BZB/wDE
0f8ACq/BX/Qn6D/4LIP/AImuooqeeXcrlj2OX/4VX4K/6E/Qf/BZB/8AE0f8Kr8Ff9CfoP8A4LIP
/ia6iijnl3Dlj2OX/wCFV+Cv+hP0H/wWQf8AxNc3Y/DXwi/xG1y2bwrojW0elafIkJ06HYrNNeBm
A24BIRAT32j0FemVy+nf8lQ8Qf8AYH03/wBH31VGUrPUlxjdaB/wqvwV/wBCfoP/AILIP/iaP+FV
+Cv+hP0H/wAFkH/xNdRRU88u5XLHscv/AMKr8Ff9CfoP/gsg/wDiaP8AhVfgr/oT9B/8FkH/AMTX
UUUc8u4csexy/wDwqvwV/wBCfoP/AILIP/iaP+FV+Cv+hP0H/wAFkH/xNdRRRzy7hyx7Hj/w7/5J
/wCGf+wXa/8Aopa6Cuf+Hf8AyT/wz/2C7X/0UtdBX1R88FFFFABRRRQAUUUUAFFFFABRRRQAUUUU
AFFFFABS+1VNQvGs40CJ5k0r+XGh6EkE8/gD+VReZdWavNeTQtCo/wCWcRBz9S1AF+iqMesQtDO7
JJH5P3hIvzflmlbVY1jjPlzAyZ2JsG9sDqBmgC7RVBdbhaOKUJIDI5jEZXLFh2PNNi1y3mKjbKuX
8skqBtbOMGgDRrn/AIif8k/8Tf8AYLuv/RTV0H6e1c/8RP8Akn/ib/sF3X/opqAPYKKKK+SPowoo
ooAKKKKAOX1H/kqHh/8A7A+pf+j7Guorl9R/5Kh4f/7A+pf+j7GuoqnsiFuwoooqSwooooAK8n8L
f8empf8AYY1P/wBLp69Yryfwt/x6an/2GNT/APS6evTwHxyPPxfwo2KKKK9o8wKKKKACsfxRn7Hp
uBkf2xpmf/A6CtpVLMAPmJ4Aqz4u0T+z/CVtNKM3DaxpP4D+0LeoqaRZUfiR2tFFFfKn0IUUUUAF
FFFAHL6d/wAlQ8Qf9gfTf/R99XUVy+nf8lQ8Qf8AYH03/wBH31dRVy3+4mOwUUUVBQUUUUAFYvwv
/wCRXuf+wxq3/pxuK2qxfhf/AMivc/8AYY1b/wBONxXo4L4mefi/hR1tFFFeueYIyhwQQCD1HY1w
nibTfsN+WSIJCwG3B713lYHi6w+0Wf2gPzH0UjI/CqW4HF+w5Ndd4U0VEjF5L8zt/qx2A9a5Lr+f
eu98MTmbR4sgDblePaqlsBprEiliqKpPBIGM1z/i6xh+wpOqBXVguQMcHNdFWb4ijWTR7jd/CN1Q
twPP85yPSko/keaK0AKKKKACiiigAooooAKKKKACiiigAooooAKKKKACs+4/5HDwV/2FJf8A0gu6
0Kz7j/kcPBX/AGFJf/SC7rGt/Cl6M0p/HH1PUKKKK+YPfCiiigAooooA5fwf/wAjD44/7DEf/pvs
66iuX8H/APIw+OP+wxH/AOm+zrqKuW/3Ex2CiiioKCiiigDl/ip/yS/xh/2B7z/0Q9dRXL/FT/kl
/jD/ALA95/6Ieuoq/sr+uxP2mFFFFQUFFFFABXL6j/yVDw//ANgfUv8A0fY11FcvqP8AyVDw/wD9
gfUv/R9jVR3IlsdRRRRUlhRRRQAUUUUAcv4P/wCRh8cf9hiP/wBN9nXUVy/g/wD5GHxx/wBhiP8A
9N9nXUVct/uJjsFFFFQUFFFFAHL/ABU/5Jf4w/7A95/6Ieuorl/ip/yS/wAYf9ge8/8ARD11FX9l
f12J+0woooqCgooooAK5fUf+SoeH/wDsD6l/6Psa6iuX1H/kqHh//sD6l/6PsaqO5EtjqKKKKksK
KKKACiiigDl/hv8A8i9d/wDYY1X/ANOFxXUVy/w3/wCReu/+wxqv/pwuK6iql8TIj8KCiiipLCii
igDl/iR/yL1p/wBhjSv/AE4W9dRXL/Ej/kXrT/sMaV/6cLeuoq/sr+uxP2mFFFFQUFFFFAHH/Fvx
XfeCfh/qus6cITeWyKY/PUsnLAcgEevrWZqnjbQ/Cfxi1qx1K+NvLNpenxRnyJGUsJ73qyqVX7y9
SOtP+L+m6h4u0X/hFLDS7yc6mUWTUEVfs9sgbkuxOc8dAO9ea/GTQfFXijxV8SLaxtNZvpLqztBp
lvpZijtTCFkIedmBcv5hmAUEAha7KVNSjZ9f+AclSo4y0PbZPHWhRaVfak+oItlZTva3EpRvklVt
jJjGSd3HA57VWuviR4cstdTR59QMWoOcLG1vLtyRkDft259s5rj9Y8ONqHxubQlKvosk8fiO7iVv
uPCRsXH+1KFY+uTXK+MNB8beIdVdbiw1u6aHxPa3MXkNDHp0dil1G3mfd3u+wHcCcdfTFNUIt2uJ
1pJXseo6T8XPCWuX1naWOrrcS3gJgIglCPjPAcrtzweM54rRm8eaDBp99fSalGtpY3YsLiXa2I5y
UAQ8df3idOPmrx7wHa6z4p+GPgLw9p+gXVnBHPHeT6xhRbJHHOzkg5yXbbtxjox57VY8UeFfEa6D
4o0Cx8P3l+2oeKo9Viu4Qvk/Zy1vkkk53Dym4x0odCN7XBVpWvY9Vs/iF4f1DXLrR7bUPP1G1kaK
eFIZD5TqqsQzbcA7XU9e9GhfELQPEmqT6bp18Zr2EEtE8EseQDglSygMOOxNYXgzw/q2g2vxLmSz
+z3upa/cXNm0uMTp9ktlRv8Ad3qw/A1yXw70DxVcePvCmqavZa8fs2lXUWo3WqNCkCXDInyQpGo/
d7t20nJI61PsYu9nsivay0dty58O/wDkn/hj/sF2v/opa6Cj4YeEZbr4Z+FpvPVS+k2jqpX1hQ46
1o3Wg3ttIyNCzhedycivobo8YzqKe0MigkxsAOuQaZTAKKKKACiiigAooooAKKKKACiiigAooooA
q6hYm8WJkfy5on3o3UZwRz7YJqvdafcahZvFcSxbyQytErBRjsea0qKAMv8Asgvp7QM0as7Deyhu
fzJPp3qe8sZprqOe3kSN1Ur865GPUVeyfy/OkoAzbDRzbfYt0gk+zg8lTlmPVqWHSmjjtQzgmOQy
ycffJB/rg1o0UAL7dK574if8k/8AE3/YLuv/AEU1dBXP/ET/AJJ/4m/7Bd1/6KagDuP7P8a/9DBo
P/gin/8Akyj+z/Gv/QwaD/4Ip/8A5MrqKK+V5mfQ8qOX/s/xr/0MGg/+CKf/AOTKP7P8a/8AQwaD
/wCCKf8A+TK6iijmYcqOX/s/xr/0MGg/+CKf/wCTKP7P8a/9DBoP/gin/wDkyuooo5mHKjzO+sfF
/wDwsbQ1bXNENydK1ApINGmCBfOs9wK/a8kklMHIxg8HII6T+z/Gv/QwaD/4Ip//AJMo1H/kqHh/
/sD6l/6Psa6iqcnZEKKuzl/7P8a/9DBoP/gin/8Akyj+z/Gv/QwaD/4Ip/8A5MrqKKnmZfKjl/7P
8a/9DBoP/gin/wDkyj+z/Gv/AEMGg/8Agin/APkyuooo5mHKjl/7P8a/9DBoP/gin/8AkyuJ8GeE
/E+oaXeTx6/pMStqupBkfR5X+YXs4Y5F0OCwJA7AgZOMn16uX+G//IvXf/YY1X/04XFawqzppuLs
ZSpxm0pGP/wg3iv/AKGTR/8AwSS//JdH/CDeK/8AoZNH/wDBJL/8l16BRV/Wq3835E/V6XY8/wD+
EG8V/wDQyaP/AOCSX/5Lo/4QbxX/ANDJo/8A4JJf/kuvQKKPrdb+b8g+r0uxw9j4T8WWEwlXX9Dl
YdPM0OY4/K8FUfiFD4xbw/bC51vQ5IzqumALFosyEN9ug2HJuzwGwSMcgEZGcj0auX+JH/IvWn/Y
Y0r/ANOFvTWJqyaTf5CeHppXSD+z/Gv/AEMGg/8Agin/APkyj+z/ABr/ANDBoP8A4Ip//kyuoorm
5mdHKjl/7P8AGv8A0MGg/wDgin/+TKP7P8a/9DBoP/gin/8Akyuooo5mHKjl/wCz/Gv/AEMGg/8A
gin/APkyj+z/ABr/ANDBoP8A4Ip//kyuooo5mHKjzOxsfF//AAsbXFXXNEFyNK08vIdGmKFfOvNo
C/a8ggh8nJzkcDBJ6T+z/Gv/AEMGg/8Agin/APkyjTv+SoeIP+wPpv8A6Pvq6iqlJ3JjFWOX/s/x
r/0MGg/+CKf/AOTKP7P8a/8AQwaD/wCCKf8A+TK6iip5mVyo5f8As/xr/wBDBoP/AIIp/wD5Mo/s
/wAa/wDQwaD/AOCKf/5MrqKKOZhyo5f+z/Gv/QwaD/4Ip/8A5MrA+HsPjEeH7kW2t6HHGNV1MFZd
Gmclvt0+85F2OC2SBjgEDJxk+j1y/wAN/wDkXrv/ALDGq/8ApwuK1hVnBNxMpU4zaUifyvHH/Qf8
P/8Agin/APkyjyvHH/Qf8P8A/gin/wDkyuhoqvrVb+b8ifq9Lsc95Xjj/oP+H/8AwRT/APyZTZLf
xvJGUbXvD5UjB/4kU/8A8mV0dFH1qt/N+QfV6XY8/bwN4rb/AJmTRv8AwSS//JdLIvi3wTHaXUmt
aTf2kuoWdrLarpMsTFZrmKElX+0sAQJMjKnp0rv65j4isF0GyYnAGs6SSf8AuIW9a08TVlNRb6kV
KFOMG0juveszxJn+x7jHpWn9ORWf4gG7R7oYz8v9a9pHkHnnpRRRWoBRRRSAKKKKACiiigAooooA
KyvCug+K/E3hfR9Y/t3R7b+0LOG78n+xpX8vzED7d32oZxnGcCtWtj4V/wDJL/B//YHs/wD0QlcG
LqzpJODsdeHpxqNqSMf/AIQbxX/0Mmj/APgkl/8Akuj/AIQbxX/0Mmj/APgkl/8AkuvQKK8z61W/
m/I7/q9Lsef/APCDeK/+hk0f/wAEkv8A8l0f8IN4r/6GTR//AASS/wDyXXoFFH1qt/N+QfV6XY8/
/wCEG8V/9DJo/wD4JJf/AJLrE1rwv4o03xH4PkOv6RLK+qSJEf7HlVUb7FdElh9qO4bQwwCOSDnj
B9brl/GH/Iw+B/8AsMSf+m+8p/Wasrpv8hOhTjqkH9n+Nf8AoYNB/wDBFP8A/JlH9n+Nf+hg0H/w
RT//ACZXUUVzczOjlRy/9n+Nf+hg0H/wRT//ACZR/Z/jX/oYNB/8EU//AMmV1FFHMw5Ucv8A2f41
/wChg0H/AMEU/wD8mUf2f41/6GDQf/BFP/8AJldRRRzMOVHmfhWx8XtrvjERa5oiSLqsYmZ9GmYO
32G05UfaxtG3aMEnkE55wOk/s/xr/wBDBoP/AIIp/wD5Mo8H/wDIw+OP+wxH/wCm+zrqKqUncmMV
Y5f+z/Gv/QwaD/4Ip/8A5Mo/s/xr/wBDBoP/AIIp/wD5MrqKKnmZXKjl/wCz/Gv/AEMGg/8Agin/
APkyj+z/ABr/ANDBoP8A4Ip//kyuooo5mHKjzP4lWPi9Phz4qa51zRJrYaVdGWOLRpo3ZfJbIVjd
sFJHQkHHoeldb/YPjX/oY9B/8EM//wAmVW+Kn/JL/GH/AGB7z/0Q9d3Xo4WEakXzI4MRKVOS5Wcb
/YPjX/oY9B/8EM//AMmUf2D41/6GPQf/AAQz/wDyZXZUV2/V6X8pye2qfzHG/wBg+Nf+hj0H/wAE
M/8A8mUf2D41/wChj0H/AMEM/wD8mV2VFH1el/KHtqn8xxv9g+Nf+hj0H/wQz/8AyZVCbwR4vn16
z1ZvEuiC5tbae1RRoU2wrK8TMSPtmcgwpjnuevGPQaKPYU/5Re2qdzjf7B8a/wDQx6D/AOCGf/5M
o/sHxr/0Meg/+CGf/wCTK7Kij6vS/lH7ap/Mcb/YPjX/AKGPQf8AwQz/APyZR/YPjX/oY9B/8EM/
/wAmV2VFH1el/KHtqn8xxv8AYPjX/oY9B/8ABDP/APJlH9g+Nf8AoY9B/wDBDP8A/JldlRR9Xpfy
h7ap/Mefab4I8X6XearcxeJdEaTUrlbqYPoUxCsIYocL/pnA2xKec8k/QX/7B8a/9DHoP/ghn/8A
kyuyoo9hT/lF7ap3ON/sHxr/ANDHoP8A4IZ//kyj+wfGv/Qx6D/4IZ//AJMrsqKPq9L+Uftqn8xx
v9g+Nf8AoY9B/wDBDP8A/JlNk0Xxqi5/4SLQTz/0AZ//AJMrtKjuP9SfU8Cj6vS/lD21T+Y4HxB4
J8XeJNB1LSbnxLoiW9/ayWsrRaFMHCuhUlSbwjOCcZBrQ/sHxr/0Meg/+CGf/wCTK7HnjjBpaPYU
9uUXtqnc43+wfGv/AEMeg/8Aghn/APkyj+wfGv8A0Meg/wDghn/+TK7Kij6vS/lH7ap/Mcb/AGD4
1/6GPQf/AAQz/wDyZR/YPjX/AKGPQf8AwQz/APyZXZUUfV6X8oe2qfzHG/2D41/6GPQf/BDP/wDJ
lUJvBHi+fXrPVm8S6ILm1tp7VFGhTbCsrxMxI+2ZyDCmOe568Y9Boo9hT/lF7ap3ON/sHxr/ANDH
oP8A4IZ//kyj+wfGv/Qx6D/4IZ//AJMrsqKPq9L+Uftqn8xxv9g+Nf8AoY9B/wDBDP8A/JlH9g+N
f+hj0H/wQz//ACZXZUUfV6X8oe2qfzHG/wBg+Nf+hj0H/wAEM/8A8mUf2D41/wChj0H/AMEM/wD8
mV2VFH1el/KHtqn8x59ongjxfoNnJbW/iXRHjkubi6Jk0KYndNM8zji8HAaQgewHXrV/+wfGv/Qx
6D/4IZ//AJMrsqKPYU/5Re2qdzjf7B8a/wDQx6D/AOCGf/5Mo/sHxr/0Meg/+CGf/wCTK7Kij6vS
/lH7ap/Mcb/YPjX/AKGPQf8AwQz/APyZR/YPjX/oY9B/8EM//wAmV2VFH1el/KHtqn8x59rfgjxf
r1nHbXHiXREjjube6Bj0KYHdDMkyDm8PBaMA+xPTrV/+wfGv/Qx6D/4IZ/8A5MrsqKPYU/5Re2qd
zjf7B8a/9DHoP/ghn/8Akyj+wfGv/Qx6D/4IZ/8A5MrsqKPq9L+Uftqn8xxv9g+Nf+hj0H/wQz//
ACZR/YPjX/oY9B/8EM//AMmV2VFH1el/KHtqn8xxv9g+Nf8AoY9B/wDBDP8A/JlctbaX4vi+JGto
uu6J9p/snTy8h0WbYVM17tAX7XkEEPk5OcjgYJPrdcXF/wAlU1//ALAum/8Ao+/rnr04U6blFam1
GpOdRKTMXR/A+veH7nUbux1TQ49Q1KUzXd1LpV1K0hJztG+9OxR2VcKPStGTS/GcsbI2v6CVYYI/
sOfof+3yuqorynUk9z0lBLY4vR/Cvibw7o9jpWl6voFpYWcXlRQ/2LcPtGSepvSepPU1c/s/xr/0
MGg/+CKf/wCTK6iik5tu7GoJaI5f+z/Gv/QwaD/4Ip//AJMo/s/xr/0MGg/+CKf/AOTK6iijmY+V
GR8Jf+SVeDP+wLZf+iErqq5X4S/8kq8Gf9gWy/8ARCV1VfSnzwySFJo2R0Dq33ge/wBawdU8JwzB
DaARMGG4HnI710NFMDzW8sZbO4eNo3AzwSOoor0h4Ul+8qt/vDNFVzAeXUUUf56VQBRR9elFABRR
RQAUUUUAFFFFABSNnadvDY4pabJGJY2QllB7qcH86AMewuBbtcNdSTLdQgvJHI5KlcnBUdMfSmQ+
IneNpSkckRj3L5TbiCeit71pQ6XDD5pJklaQbWaVtxx6fTr+dMXR4Vtng3ysjY+85yMdMelACWd5
cyahLbzpHhVDbosnBJ6Gr/8AOqtnpsNlJI6bmaTG9nbJOKtUAFc/8RP+Sf8Aib/sF3X/AKKaugrn
/iJ/yT/xN/2C7r/0U1AHsFFFFfJH0YUUUUAFFFFAHL6j/wAlQ8P/APYH1L/0fY11FcvqP/JUPD//
AGB9S/8AR9jXUVT2RC3YUUUVJYUUUUAFcv8ADf8A5F67/wCwxqv/AKcLiuorl/hv/wAi9d/9hjVf
/ThcVX2WR9pHUUUUVJYUUUUAFcv8SP8AkXrT/sMaV/6cLeuorl/iR/yL1p/2GNK/9OFvVw+JEy+F
nUUUUVBQUUUUAFFFFAHL6d/yVDxB/wBgfTf/AEffV1Fcvp3/ACVDxB/2B9N/9H31dRVy3+4mOwUU
UVBQUUUUAFcv8N/+Reu/+wxqv/pwuK6iuX+G/wDyL13/ANhjVf8A04XFV9lkfaR1FFFFSWFFFFAB
XLfEqPzvDlrGTgPrGlLn66hb11Ncz8Qv+QHY/wDYa0n/ANOFvWtL+JH1RlU+CXodwq7VAHQcCq2q
Z/s642jJ2GrVIyhlIYZUjkV9GeCeW/X6UVb1aNYdSnRAVUNwDTLGza+ulhUgM3Td0rUCvz9aK0de
s47LUCkXAwCV9M1nUAFFFFABRRRQAUUUUAFbHwr/AOSX+D/+wPZ/+iErHrY+Ff8AyS/wf/2B7P8A
9EJXl4/4YnfhPiZ1FFFFeMeoFFFFABXL+MP+Rh8D/wDYYk/9N95XUVy/jD/kYfA//YYk/wDTfeVU
dyJbHUUUUVJYUUUUAFFFFAHL+D/+Rh8cf9hiP/032ddRXL+D/wDkYfHH/YYj/wDTfZ11FXLf7iY7
BRRRUFBRRRQBy/xU/wCSX+MP+wPef+iHru64T4qf8kv8Yf8AYHvP/RD13devgvhZ5eL+JBRRRXon
AFFFFABRRRQAUUUUAFFFFABRRRQAUUUUAFFFFABTXXeuD9adRQAyNiwYHk7utPqJW2OVbjJyKd5y
bgCwoAfRRRQAUUUUAFFFFABRRRQAUUUUAFFFFABRRRQAUUUUAFFFFABRRRQAUUUUAFFFFABXFxf8
lU1//sC6b/6Pv67SuLi/5Kpr/wD2BdN/9H39cuK/gy/rqdOH/io6GiiivBPaCiiigAooooAyPhL/
AMkq8Gf9gWy/9EJXVVyvwl/5JV4M/wCwLZf+iErqq+oPnAooooAKKKKAPO7nRbu2ujB5TSN/eQEg
/jWrZ+C5JYw1xN5LH+FRkiuv6c4/XmjuarmA5S48FMseYbjfJ6MuBXPXVnLZztFKm1h+Rr0yqGsa
WmpWrptXzcYVz296FLuB53RVrUNOl024MMuN2OGHQj1qrVgFFFFABRRRQAUUUUAFFFFABRRRQAVh
+PLeW88D+IoIInnnl064SOKNSzOxiYAADkkntW5RQBof8LY8Pf3dY/8ABDf/APxmj/hbHh7+7rH/
AIIb/wD+M1n0V531Gn3Z2/W59kaH/C2PD393WP8AwQ3/AP8AGaP+FseHv7usf+CG/wD/AIzWfRR9
Rp92H1ufZGh/wtjw9/d1j/wQ3/8A8Zo/4Wx4e/u6x/4Ib/8A+M1n0UfUafdh9bn2Rn3XxH0a6+I2
iXEUWsSRxaVfxsF0O935aazIwnk7iPkOSBgcZI3DPUf8LI0n/n017/wndQ/+MVz+i/8AJUNJ/wCw
Pf8A/o+yr0ivOxEI0p8i6HZRlKpHmOX/AOFkaT/z6a9/4Tuof/GKP+FkaT/z6a9/4Tuof/GK6iiu
f3ex0e93OX/4WRpP/Ppr3/hO6h/8Yo/4WRpP/Ppr3/hO6h/8YrqKKPd7B73c5f8A4WRpP/Ppr3/h
O6h/8Yrm/AHj/TLXQrpHtdbYnVdSk/d6DfSDDX07DlYSM4IyOoOQQCCK9Mrl/hv/AMi9d/8AYY1X
/wBOFxVe7yvQj3uZah/wsjSf+fTXv/Cd1D/4xR/wsjSf+fTXv/Cd1D/4xXUUVPu9i/e7nL/8LI0n
/n017/wndQ/+MUf8LI0n/n017/wndQ/+MV1FFHu9g97ucv8A8LI0n/n017/wndQ/+MVzfj/x/pl1
oVqiWutqRqumyfvNBvoxhb6Bjy0IGcA4HUnAAJIFemVy/wASP+RetP8AsMaV/wCnC3qo8vMtCZc3
K9Q/4WRpP/Ppr3/hO6h/8Yo/4WRpP/Ppr3/hO6h/8YrqKKn3exXvdzl/+FkaT/z6a9/4Tuof/GKP
+FkaT/z6a9/4Tuof/GK6iij3ewe93OX/AOFkaT/z6a9/4Tuof/GKP+FkaT/z6a9/4Tuof/GK6iij
3ewe93PM7Hx/pi/EbXLg2ut+XJpWnxgDQb4vlZrwnKeTuA+YYJGDg4J2nHSf8LI0n/n017/wndQ/
+MUad/yVDxB/2B9N/wDR99XUVUuW+xMea25y/wDwsjSf+fTXv/Cd1D/4xR/wsjSf+fTXv/Cd1D/4
xXUUVPu9ive7nL/8LI0n/n017/wndQ/+MUf8LI0n/n017/wndQ/+MV1FFHu9g97ucv8A8LI0n/n0
17/wndQ/+MVzfgDx/plroV0j2utsTqupSfu9BvpBhr6dhysJGcEZHUHIIBBFemVy/wAN/wDkXrv/
ALDGq/8ApwuKr3eV6Ee9zLUP+FkaT/z6a9/4Tuof/GKP+FkaT/z6a9/4Tuof/GK6iip93sX73c5f
/hZGk/8APpr3/hO6h/8AGKP+FkaT/wA+mvf+E7qH/wAYrqKKPd7B73c5f/hZGk/8+mvf+E7qH/xi
sPxh4207V7HTLSC31eOWTWtKw11o15bxjF/bnmSSJVHTuRk4HU16JXM/EP8A5Adj/wBhrSf/AE4W
9aUuX2kdOqMqnNyS9DuaKKK+hPDOe1jwubyeS4hl/et/A3A6VZ0HR/7Ntf8ASFQyBiwb0FbFVdUV
n024UNtJQ4YU7gcR4hy2qTMJVmDHhlOeKzqB3/wpK0AKKKKACiiigAooooAKp/DXx/pln8OfCtvJ
a620kWlWsbGLQb6RCRCoO11hKsPQgkHsauVsfCv/AJJf4P8A+wPZ/wDohK8zHW5Y3O7C35nYP+Fk
aT/z6a9/4Tuof/GKP+FkaT/z6a9/4Tuof/GK6iivI93sen73c5f/AIWRpP8Az6a9/wCE7qH/AMYo
/wCFkaT/AM+mvf8AhO6h/wDGK6iij3ewe93OX/4WRpP/AD6a9/4Tuof/ABiub8VeP9Mn13wc62ut
gQ6rJI2/Qb5SR9hu1+UGHLHLDhcnGTjAJHplcv4w/wCRh8D/APYYk/8ATfeVUeW+xEua24f8LI0n
/n017/wndQ/+MUf8LI0n/n017/wndQ/+MV1FFT7vYv3u5y//AAsjSf8An017/wAJ3UP/AIxR/wAL
I0n/AJ9Ne/8ACd1D/wCMV1FFHu9g97ucv/wsjSf+fTXv/Cd1D/4xR/wsjSf+fTXv/Cd1D/4xXUUU
e72D3u55r4T8eadFrnjGQ2euMs2rRuvl6DfOQPsNouGAhJU5U8Ng4IOMEE9J/wALD0z/AJ8fEH/h
Oah/8Yqz4D/5Dnjr/sNR/wDpvs67CvUjhYTipNvVI82WJnCTirHDf8LD0z/nx8Qf+E5qH/xij/hY
emf8+PiD/wAJzUP/AIxXc0VX1On3ZP1ufZHDf8LD0z/nx8Qf+E5qH/xij/hYemf8+PiD/wAJzUP/
AIxXc0UfU6fdh9bn2R5R8QPGFrrfgPxJp1lpniCa8vNNubeCP/hHr9d8jxMqjJhAGSRyTivV6KK6
aVGNFNRMKlWVV3YUUUVsYhRRRQAUUUUAFFFFABRRRQAUUUUAFFFFABRRRQAUUUUAIyhhgjNMaMCN
goGeoqSkJAXJPbmgBI23RqfanUyHIQ/Xj6U+gAooooAKKKKACiiigAooooAKKKKACiiigAooooAK
KKKACiiigAooooAKKKKACvPdX1ZfDvxK1S6u7LVJba60ixjimsdLubtC6TXhdS0UbAECRDg4+8K9
CorOpBVIuLLhN05cyOG/4WHpn/Pj4g/8JzUP/jFH/Cw9M/58fEH/AITmof8Axiu5ork+p0+7Or63
Psjhv+Fh6Z/z4+IP/Cc1D/4xR/wsPTP+fHxB/wCE5qH/AMYruaKPqdPuw+tz7I4b/hYemf8APj4g
/wDCc1D/AOMVH/wszRvO8r7Nrvm4z5f/AAj2obseuPIrvaxF8n/hID937RgD/gOTj9c0fU6fdh9b
n2RV+GNpPp/w18J2t1DJbXMOkWkcsMyFHjdYUDKynkEEEEGulpaSu84gooooAKKKKACiiigAo/lR
RQBWutPt74qZ4lkI6GsLXPC0YjaazUIV6x54P0rpqRhuUg9Kd2B5bRVvVLZrS+mjK7cOSo9j0qp9
OlaAFFFFABRRRQAUUUUAFFFFABRRRQAUUUUAFFFFABRRRQBX0X/kqGk/9ge//wDR9lXpFeb6L/yV
DSf+wPf/APo+yr0ivAxn8ZnsYX+GFFFFcJ1hRRRQAVy/w3/5F67/AOwxqv8A6cLiuorl/hv/AMi9
d/8AYY1X/wBOFxVfZZH2kdRRRRUlhRRRQAVy/wASP+RetP8AsMaV/wCnC3rqK5f4kf8AIvWn/YY0
r/04W9XD4kTL4WdRRRRUFBRRRQAUUUUAcvp3/JUPEH/YH03/ANH31dRXL6d/yVDxB/2B9N/9H31d
RVy3+4mOwUUUVBQUUUUAFcv8N/8AkXrv/sMar/6cLiuorl/hv/yL13/2GNV/9OFxVfZZH2kdRRRR
UlhRRRQAVzPxD/5Adj/2GtJ/9OFvXTVzPxD/AOQHY/8AYa0n/wBOFvWtL+JH1RlU+CXodzRRRX0Z
4IVW1KGW6s5IYSA7jaC3SrNFAHm+oaXPpcgScbc9GHeqldR40Em6Elh5WPlHfNc2sDyZKqcYJHHp
WoEdFFFABRRRQAUUUUAFbHwr/wCSX+D/APsD2f8A6ISsetj4V/8AJL/B/wD2B7P/ANEJXl4/4Ynf
hPiZ1FFFFeMeoFFFFABXL+MP+Rh8D/8AYYk/9N95XUVy/jD/AJGHwP8A9hiT/wBN95VR3IlsdRRR
RUlhRRRQAUUUUAYXgP8A5Dnjr/sNR/8Apvs67CuP8B/8hzx1/wBhqP8A9N9nXYV9HS/hx9EeBU+O
XqFFFFamYUUUUAFFFFABRRRQAUUUUAFFFFABRRRQAUUUUAFFFFABRRRQAUUUUAFFFFABTJf9W30N
PprLuQj16UAEf3B9KdUUcqqoDE7gPSkjRpMlnPXgAUATUVE0ezlAd2fWl83ruQj0xQBJRTVcNyOv
pTqACiiigAooooAKKKKACiiigAooooAKKKKACiiigAooooAKKKKACiiigAooooAKKKKACuaj58Yv
/wBcV/8AQmrpf5VhxSRf28UwPPwCeP4cnH9aAN2kpaSgAooooAKKKKACiiigAooooAKKKKAOJ8YK
v9rAgncUBPPtWFXS+NLMrcx3AGUZdrH0IrmuK1WwBRRkUd6ACiiigAooooAKKKKACiiigAooooAK
KKKACiiigCvov/JUNJ/7A9//AOj7KvSK8t1DR57nVLTUbPVrzSLy3hltxJaLC26ORo2YESxuOsSc
gA9ad9n8Q/8AQ66x/wCA9h/8jV5eIws6s+aLR30cRGnDlZ6hRXl/2fxD/wBDrrH/AID2H/yNR9n8
Q/8AQ66x/wCA9h/8jVz/AFGr3Rv9bh2Z6hRXl/2fxD/0Ousf+A9h/wDI1H2fxD/0Ousf+A9h/wDI
1H1Gr3QfW4dmeoVy/wAN/wDkXrv/ALDGq/8ApwuK5f7P4h/6HXWP/Aew/wDkak+G3hrVb7wzJOPG
OtW27UtRykMNiVLC9nBb5rYnLEFjzjJOABgDOph5UY3k0VCtGpL3Ueo0Vy//AAh+rf8AQ8a9/wB+
NP8A/kWj/hD9W/6HjXv+/Gn/APyLXLyrudN32Ooorl/+EP1b/oeNe/78af8A/ItH/CH6t/0PGvf9
+NP/APkWjlXcLvsdRXL/ABI/5F60/wCwxpX/AKcLej/hD9W/6HjXv+/Gn/8AyLXN+P8AwrqcGhWr
P4x1u4B1XTV2SQ2IAJvoAG+W2BypIYc4yBkEZBqKXMtSZN8r0PTKK5f/AIQ/Vv8AoeNe/wC/Gn//
ACLR/wAIfq3/AEPGvf8AfjT/AP5FqeVdyrvsdRRXL/8ACH6t/wBDxr3/AH40/wD+RaP+EP1b/oeN
e/78af8A/ItHKu4XfY6iiuX/AOEP1b/oeNe/78af/wDItH/CH6t/0PGvf9+NP/8AkWjlXcLvsGnf
8lQ8Qf8AYH03/wBH31dRXmdj4V1NviNrkQ8Y62si6Vp7GcQ2O9wZrwBT/o23A2kjAB+Y5J4x0n/C
H6t/0PGvf9+NP/8AkWqklfcmLdtjqKK5f/hD9W/6HjXv+/Gn/wDyLR/wh+rf9Dxr3/fjT/8A5Fqe
VdyrvsdRRXL/APCH6t/0PGvf9+NP/wDkWj/hD9W/6HjXv+/Gn/8AyLRyruF32Oorl/hv/wAi9d/9
hjVf/ThcUf8ACH6t/wBDxr3/AH40/wD+Ra5vwB4V1OfQrpk8Y63bgarqS7I4bEgkX04LfNbE5Ygs
ecZJwAMAVyrlepF3zLQ9Morl/wDhD9W/6HjXv+/Gn/8AyLR/wh+rf9Dxr3/fjT//AJFqeVdy7vsd
RRXL/wDCH6t/0PGvf9+NP/8AkWj/AIQ/Vv8AoeNe/wC/Gn//ACLRyruF32OormfiH/yA7H/sNaT/
AOnC3pv/AAh+rf8AQ8a9/wB+NP8A/kWuc8feFtUt9DtHbxlrdwP7W0xQskNiACb6ABvltgcqSGHb
IGQRkG6dlOLv1M6l3Bqx69RXEf8ACMa1/wBD3r3/AID6d/8AIlH/AAjGtf8AQ969/wCA+nf/ACJX
rfW6R5v1WodvRXEf8IxrX/Q969/4D6d/8iUf8IxrX/Q969/4D6d/8iUfW6QfVah2NxZQ3qlZo1kH
Ykc/nWPrOlG30mSKzjLY56/Mo74P9Kxv+EX1r/oete/8B9O/+RKP+EY1r/oete/8B9O/+RKPrlIP
qtQwz1OMUVd8K6HJH4413TdQ1O61qGGwsruJ7xIEZHkkulcDyY4wQRCnUHv61ueIPDIRFlsoyTnD
ItdsJqaUkc0ouL5WctRWk/h+/VA/2ZyD2AzTP7Bv9u77LJ9NprQkoUVLLazW+BLE0Z/2hirlr4fv
rtQUgYD1b5f50AZ9a/wr/wCSX+D/APsD2f8A6ISlt/Cd9NLtdBGP7xNc18NfCup3Hw58Kyx+Mdbt
Y5NKtWWCKGxKRgwqQq7rYtgdBkk8ck15mO1jHU7sL8TPTKK5f/hD9W/6HjXv+/Gn/wDyLR/wh+rf
9Dxr3/fjT/8A5FryOVdz07vsdRRXL/8ACH6t/wBDxr3/AH40/wD+RaP+EP1b/oeNe/78af8A/ItH
Ku4XfY6iuX8Yf8jD4H/7DEn/AKb7yj/hD9W/6HjXv+/Gn/8AyLXN+KvCupx674OVvGOtzGTVZFV3
hscxH7DdncuLYDOAV+YEYY8ZwRUYq+5Em7bHplFcv/wh+rf9Dxr3/fjT/wD5Fo/4Q/Vv+h417/vx
p/8A8i1PKu5d32Ooorl/+EP1b/oeNe/78af/APItH/CH6t/0PGvf9+NP/wDkWjlXcLvsdRRXL/8A
CH6t/wBDxr3/AH40/wD+RaP+EP1b/oeNe/78af8A/ItHKu4XfYt+A/8AkOeOv+w1H/6b7Ouwrhfh
hZzaffeNYJ7641KVNaTN1dLGsj5sLM8iNEXjOOFHAHU813VfQUv4cfRHhVPjl6hRRRWpmFFFFABR
RRQAUUUUAFFFFABRRRQAUUUUAFFFFABRRRQAUUUUAFFFFABRRRQAUUUUAFFFFABRRRQBG8ZzuX71
H71lycKakooAZHIJFU9/Sn1DJHtkDhcgdRUqsGUEUALRRRQAUUUUAFFFFABRRRQAUUUUAFFFFABR
RRQAUUUUAFFFFABRRRQAUUUUAFYcU0X9vGPH7/AYnH8OTgZrcrmoc/8ACXt1/wBSv/oTUAdNSUtJ
QAUUUUAFFFFABRRnv0ooAKKKKACiiigBk0EdwmyWNZFznDDNVToti3/LpF/3yKu0UAYmreHLeezk
+zxJFKoyMcZriGUqxB6jg16JrVib6wkRSwdRldvevPZI3jkKSKVcdQa0iAyiiimAUUUUAFFFFABR
RRQAUUUUAFFFFABRRRQAUUUUAFFFFABRRRQAVofCf/kT2/7Cmp/+l89Z9aHwn/5E9v8AsKan/wCl
89edjv4a9Ttwnxv0Owooorwz1gooooAK5f4kf8i9af8AYY0r/wBOFvXUVy/xI/5F60/7DGlf+nC3
q4fEiZfCzqKKKKgoKKKKACiiigDl9O/5Kh4g/wCwPpv/AKPvq6iuX07/AJKh4g/7A+m/+j76uoq5
b/cTHYKKKKgoKKKKACuX+G//ACL13/2GNV/9OFxXUVy/w3/5F67/AOwxqv8A6cLiq+yyPtI6iiii
pLCiiigArl/iR/yL1p/2GNK/9OFvXUVy/wASP+RetP8AsMaV/wCnC3q4fEiZfCzqKKKKgoKKKKAC
iiigDA0H/kqHiP8A7A+mf+j7+uyrjdB/5Kh4j/7A+mf+j7+uyr6Gh/CieHW/iMP50e/eiitzAayK
/wB4Zp3pRRQAfrXCfCv/AJJf4P8A+wPZ/wDohK7uuE+Ff/JL/B//AGB7P/0Qlebjfhid+E+JnUUU
UV5J6gUUUUAFcv4w/wCRh8D/APYYk/8ATfeV1Fcv4w/5GHwP/wBhiT/033lVHciWx1FFFFSWFFFF
ABRRRQBheA/+Q546/wCw1H/6b7Ouwrj/AAH/AMhzx1/2Go//AE32ddhX0dL+HH0R4FT45eoUUUVq
ZhRRRQAUUUUAFFFFABRRRQAUUUUAFFFFABRRRQAUUUUAFFFFABRRRQAUUUUAFFFFABRRRQAUUUUA
FFFFAB/Dx1qJS6fKE/E9KlopgR7nXlgMe1HnJ/fGfTvUmKTaM5wKQEX2gluF4qb9aY0Ks2ct+dN8
kg/K+BQBIGB70tV0zGzAAsx6VIJ175H4GgCSio/PT1P5GnJIsgyD+lADqKKKACiiigAooooAKKKK
ACiiigAooooAKKKKACsOOeP/AISAw4/e7Q2cfw5IFblYUVwv/CQNBg+ZgPux2JIx+lAG9SUtJQAU
UUUAFFFFAHnVrrN5Z/6qdgPRjkVsWnjR14uYdw/vR8GuZorUD0y1vIbyFZYnBRvU81PXl6TSRrhX
Zfo2K1dL8R3FjIFlYzQ9we3vU8oHd0VHBMtxCkicowyKkqACiiigA/wrmPGVrF5MNwAFkL7Tjvwa
6SaRYY2kb7qjJrz7VtWm1SYlyBGpyqjtVRAoYxRRRVgFFFFABRRRQAUUUUAFFFFABRRRQAUUUUAF
FFFABRRRQAUUUUAFaHwn/wCRPb/sKan/AOl89Z9UPh14k1HT/Ds0EHhXV9SiTVNSxdWstmsb5vpz
wJLhG4zjlRyD1HNefjlemvU7MK7Tfoen0Vy//CYat/0I+vf9/wDT/wD5Ko/4TDVv+hH17/v/AKf/
APJVeLys9XmR1FFcv/wmGrf9CPr3/f8A0/8A+SqP+Ew1b/oR9e/7/wCn/wDyVRysOZHUVy/xI/5F
60/7DGlf+nC3o/4TDVv+hH17/v8A6f8A/JVc34/8VanPoVqr+DtbtwNV01t8k1iQSL6AhfluScsQ
FHGMkZIGSKjF8yJlJcrPTKK5f/hMNW/6EfXv+/8Ap/8A8lUf8Jhq3/Qj69/3/wBP/wDkqp5WVzI6
iiuX/wCEw1b/AKEfXv8Av/p//wAlUf8ACYat/wBCPr3/AH/0/wD+SqOVhzI6iiuX/wCEw1b/AKEf
Xv8Av/p//wAlUf8ACYat/wBCPr3/AH/0/wD+SqOVhzINO/5Kh4g/7A+m/wDo++rqK8zsfFWpr8Rt
clHg7W2kbStPUwCax3oBNeEMT9p24O4gYJPynIHGek/4TDVv+hH17/v/AKf/APJVVKLuTGSsdRRX
L/8ACYat/wBCPr3/AH/0/wD+SqP+Ew1b/oR9e/7/AOn/APyVU8rK5kdRRXL/APCYat/0I+vf9/8A
T/8A5Ko/4TDVv+hH17/v/p//AMlUcrDmR1Fcv8N/+Reu/wDsMar/AOnC4o/4TDVv+hH17/v/AKf/
APJVc34A8VanBoV0qeDtbuAdV1Jt8c1iACb6clfmuQcqSVPGMg4JGCa5XysjmXMj0yiuX/4TDVv+
hH17/v8A6f8A/JVH/CYat/0I+vf9/wDT/wD5KqeVl8yOoorl/wDhMNW/6EfXv+/+n/8AyVR/wmGr
f9CPr3/f/T//AJKo5WHMjqK5f4kf8i9af9hjSv8A04W9H/CYat/0I+vf9/8AT/8A5Krm/H/irU59
CtVfwdrduBqumtvkmsSCRfQEL8tyTliAo4xkjJAyRUYvmRMpLlZ6ZRXL/wDCYat/0I+vf9/9P/8A
kqj/AITDVv8AoR9e/wC/+n//ACVU8rK5kdRRXL/8Jhq3/Qj69/3/ANP/APkqj/hMNW/6EfXv+/8A
p/8A8lUcrDmR1FFcv/wmGrf9CPr3/f8A0/8A+SqP+Ew1b/oR9e/7/wCn/wDyVRysOZFnQf8AkqHi
P/sD6Z/6Pv67KvPvBGpXGqfEbxLLc6VeaPIulaaogvXhZ2HnXx3AxSOuOccnPB46Z9Br3qH8OJ4l
b+IwooorcxCiiigArhPhX/yS/wAH/wDYHs//AEQld3Xl/gq+8Q+G/Bug6Tc+B9be5sLC3tZWiudP
KFkjVSVJugcZHGQK4cXCU0uVXOzDTjBvmZ3tFc3/AMJPrX/Qia9/4Ead/wDJdH/CT61/0Imvf+BG
nf8AyXXm/V6v8p6Htqf8x0lFc3/wk+tf9CJr3/gRp3/yXR/wk+tf9CJr3/gRp3/yXR9Xq/yh7an/
ADHSVy/jD/kYfA//AGGJP/TfeVJ/wk+tf9CJr3/gRp3/AMl1ja9feIdU1Tw5cxeB9bWPTb97qYPc
6eCym1uIcL/pXJ3SqeccA/QuNCpf4SZVqdtzvaK5v/hJ9a/6ETXv/AjTv/kuj/hJ9a/6ETXv/AjT
v/kul9Xq/wApXtqf8x0lFc3/AMJPrX/Qia9/4Ead/wDJdH/CT61/0Imvf+BGnf8AyXR9Xq/yh7an
/MdJRXN/8JPrX/Qia9/4Ead/8l0f8JPrX/Qia9/4Ead/8l0fV6v8oe2p/wAxP4D/AOQ546/7DUf/
AKb7Ouwrkfh/aajHP4nvdQ0y40g6hqa3ENvdSRPJ5YtLaLJ8p3UZaJ+N2cAV11e5TTUIp9jx6jvN
tdwooorQzCiiigAooooAKKKKACiiigAooooAKKKKACiiigAooooAKKKKACiiigAooooAKKKKACii
igAooooAKKKKACiiigAooooAKKKKAEpevbmiigA/Co2jO7cp2t/OpKKAI1l2j512/TpTlmRzgdad
TWjV+qn8KYDqKi2SJ91gw9GpRNj74Kn6ZFAElFRecD0DN+lPSTdxjB9KAHUUUUgCiiigAooooAKK
KKACuaiU/wDCXs2DjylGcf7TV0vv6Vhxz/8AE+MGw5ADb+3JPFAG7SUtJQAUUUUAFFFFAHllFFFa
gFFFFAF631q9tYwkNwyoO20HFb+g+JmnmMN24DH7jEYz9a5KlBKkEdRRYD1Ljg5yPWiuMsvGFxbx
lJkWbH3e1btr4nsrhU3OIXbqrdqzswNC8iE1rMh/iUj9K80ZdrEenFekXFyPsEs0Z3hUJBXvXmzH
cxPcnNVEBKKKKoAooooAKKKKACiiigAooooAKKKKACiiigAooooAKKKKACiiigArQ+E//Int/wBh
TU//AEvnrPrQ+E//ACJ7f9hTU/8A0vnrzsd/DXqduE+N+h2FFFFeGesFFFFABXL/ABI/5F60/wCw
xpX/AKcLeuorl/iR/wAi9af9hjSv/Thb1cPiRMvhZ1FFFFQUFFFFABRRRQBy+nf8lQ8Qf9gfTf8A
0ffV1Fcvp3/JUPEH/YH03/0ffV1FXLf7iY7BRRRUFBRRRQAVy/w3/wCReu/+wxqv/pwuK6iuX+G/
/IvXf/YY1X/04XFV9lkfaR1FFFFSWFFFFABXL/Ej/kXrT/sMaV/6cLeuorl/iR/yL1p/2GNK/wDT
hb1cPiRMvhZ1FFFFQUFFFFABRRRQBgaD/wAlQ8R/9gfTP/R9/XZVxug/8lQ8R/8AYH0z/wBH39dl
X0ND+FE8Ot/EYUUUVuYBRRRQAUUUUAFFFFABRRRQAUUUUAFFFFABRRRQAUUUUAFFFFABRRRQAUUU
UAFFFFABRRRQAUUUUAFFFFABRRRQAUUUUAFFFFABRRRQAUUUUAFFFFABRRRQAUUUUAFFFFABRRRQ
AUUUUAFFFFABRRRQAUUUUAFFFFABRRRQAUUUUAFMdCxBU4b6U+igBirJuy7fgKfRRQAUUUUAFFFF
ABRRRQAVhRXX/FQG228gCTdn1JH9K3a5uGNv+EsZtvyeUBn33NxQB0tJS0lABRRRQAUUUUAeWUUU
VqAUUUUAFFFFAB1yDzQeaKKANHTdcuNNYhWEkeMGOTpVKaQTTNIFCbjnaOgqM9MUtAFu8js44oxb
yPJLj5yR8tU6KKACiigZbOASfSgAop8sMkEhSRDGw7NTP4c/nQAUVu23hkyaXJdvLjCFlVe+BmsO
gBKKKKACiiigAooooAKKKKACiiigAooooAK0PhP/AMie3/YU1P8A9L56z60PhP8A8ie3/YU1P/0v
nrzsd/DXqduE+N+h2FFFFeGesFFFFABXL/Ej/kXrT/sMaV/6cLeuorl/iR/yL1p/2GNK/wDThb1c
PiRMvhZ1FFFFQUFFFFABRRRQBy+nf8lQ8Qf9gfTf/R99XUVy+nf8lQ8Qf9gfTf8A0ffV1FXLf7iY
7BRRRUFBRRRQAVy/w3/5F67/AOwxqv8A6cLiuorl/hv/AMi9d/8AYY1X/wBOFxVfZZH2kdRRRRUl
hRRRQAVy/wASP+RetP8AsMaV/wCnC3rqK5f4kf8AIvWn/YY0r/04W9XD4kTL4WdRRRRUFBRRRQAU
UUUAYGg/8lQ8R/8AYH0z/wBH39dlXG6D/wAlQ8R/9gfTP/R9/XZV9DQ/hRPDrfxGFFFFbmAUUUUA
FFFFABRRRQAUUUUAFFFFABRRRQAUUUUAFFFFABRRRQAUUUUAFFFFABRRRQAUUUUAFFFFABRRRQAU
UUUAFFFFABRRRQAUUVW/tCH7PcTAkx25YSHaeNvWgCzRVSPVbaaG0lSTcl02yI4PzHBP8gaLzVIb
GWKJxI8koZlWONnOBjJ4HuKALdFVf7UtjatceZiJDhs9R7Y9fakt9ShupDGBJHJjOyaMoSPXkc0A
W6KrSajbxaglkz4uHUuoI4wDyc0h1K3W1ubgviK3LrI2Om3Ofr0oAtUVVi1GKS1e4IkiiUbiZY2X
j15HSn2d6l7GXRJVXjmSMrnPcZ60AT0VFb3Ud3CssRyjZwSMdCR3+hqOz1CG/wDO8li3lOUbgjkA
fn/9agCzRRRQAUUUUAFFFFABRRRQAUUUUAFFFFABRRRQAUUUUAFFFFABRRRQAUUUUAFFFFABRRRQ
AViRyv8A295XlnZgN5nvk8f59a26wkuj/wAJIbbHyhRLnPckj+lAG9SUtJQAUUhYKCT90VF54YYA
IagCbBoquVlVQM++aKegHmlFFFaAFFFFABRRRQAUUUUAFFFFABRRRQAUq8MD1wc0lFAGlrmoJqhh
kUEME2tx3rP/AIicCnQTeRNHJgMUbJB6H2rorqysNc2yWcyQ3LDJiYYGcdKNgH+E75biGSxlOcqd
v0xg1zl5CLe6ljGcK2OafPbz6bc7HzFIOeD/ACqBmZmLMdxPU5oAbRRRQAUUUUAFFFFABRRRQAUU
UUAFFFFABVD4deCdO1fw7Ndz3GrxyyapqWVtdZvLeMYvpxxHHKqjp2Aycnqav1ofCf8A5E9v+wpq
f/pfPXn45tU1budmFSc3fsWP+Fb6T/z969/4UWof/H6P+Fb6T/z969/4UWof/H66iivF55dz1eWP
Y5f/AIVvpP8Az969/wCFFqH/AMfo/wCFb6T/AM/evf8AhRah/wDH66iijnl3Dlj2OX/4VvpP/P3r
3/hRah/8frm/H/gDTLXQrV0utbYnVdNj/ea9fSDDX0CnhpiM4JweoOCCCAa9Mrl/iR/yL1p/2GNK
/wDThb1UZS5lqTKMeV6B/wAK30n/AJ+9e/8ACi1D/wCP0f8ACt9J/wCfvXv/AAotQ/8Aj9dRRU88
u5XLHscv/wAK30n/AJ+9e/8ACi1D/wCP0f8ACt9J/wCfvXv/AAotQ/8Aj9dRRRzy7hyx7HL/APCt
9J/5+9e/8KLUP/j9H/Ct9J/5+9e/8KLUP/j9dRRRzy7hyx7Hmdj4A0xviNrlubrW/Lj0rT5Aw16+
D5aa8By/nbiPlGATgZOANxz0n/Ct9J/5+9e/8KLUP/j9Gnf8lQ8Qf9gfTf8A0ffV1FVKUr7kxjG2
xy//AArfSf8An717/wAKLUP/AI/R/wAK30n/AJ+9e/8ACi1D/wCP11FFTzy7lcsexy//AArfSf8A
n717/wAKLUP/AI/R/wAK30n/AJ+9e/8ACi1D/wCP11FFHPLuHLHscv8A8K30n/n717/wotQ/+P1z
fgDwBpl1oV073WtqRqupR/u9evoxhb6dRwswGcAZPUnJJJJNemVy/wAN/wDkXrv/ALDGq/8ApwuK
rmlyvUjljzLQP+Fb6T/z969/4UWof/H6P+Fb6T/z969/4UWof/H66iip55dy+WPY5f8A4VvpP/P3
r3/hRah/8fo/4VvpP/P3r3/hRah/8frqKKOeXcOWPY5f/hW+k/8AP3r3/hRah/8AH65vx/4A0y10
K1dLrW2J1XTY/wB5r19IMNfQKeGmIzgnB6g4IIIBr0yuX+JH/IvWn/YY0r/04W9VGUuZakyjHleg
f8K30n/n717/AMKLUP8A4/R/wrfSf+fvXv8AwotQ/wDj9dRRU88u5XLHscv/AMK30n/n717/AMKL
UP8A4/R/wrfSf+fvXv8AwotQ/wDj9dRRRzy7hyx7HL/8K30n/n717/wotQ/+P0f8K30n/n717/wo
tQ/+P11FFHPLuHLHseaaf4D03/hY2uW4u9cWNNK0+QMuvXwclprwHLibcR8owCcDJwBuOel/4V5p
n/P94g/8KPUP/j9N07/kqHiD/sD6b/6Pvq6itJVJrRSZmqcHukcz/wAK80z/AJ/vEH/hR6h/8fo/
4V5pn/P94g/8KPUP/j9dNRU+1qfzP7x+zh/Kjmf+FeaZ/wA/3iD/AMKPUP8A4/R/wrzTP+f7xB/4
Ueof/H66aij2tT+Z/eHs4fyo5n/hXmmf8/3iD/wo9Q/+P1p/DG8n1D4a+E7q6mkubmbSLSSWaZy7
yO0KFmZjySSSSTWnWP8ACX/klfgz/sC2X/ohK9LBzlLm5nfY4MVGMeXlVjq6KKK9E4AooooAKKKK
ACiiigAooooAKKKKACiiigAooooAKKKKACiiigAooooAKKKKACiiigAooooAKKKKACiiigArIGnz
/wBl6rDs/eTvMY1yPm3D5a16P0oAwG0e6t73TzCubZJBLMAR8jBGXI+uf0q5qEdwuqWVzBbNcJGk
iMEcKRuKEdSOODWn6ev6Ue/egDDfS7lreSUKPOe5Fz5OeMAAbfyFWoo7i9voLiW3e1SFWwGZWLE8
dAT2rSHHaj8aAMnUNJkvdSaTlE+z4SUHO1w2QRUFvp963h/U4JYgt1P5xVFYEfNnAB/Gt33AxzR/
kGgDKtLd/wCzZIZraZ/lwY5pVYuMYwDmpNGjuYRIs0bwwceVHK4Zh1zkgnjpWj/KjH5HrQBl2Nvc
2eh+SI/9IG/aoIHVjj9DmodN0u60y7jZpRcRtHtkbaAQ2c/jyx/KtqjjtQAUUUUAFFFFABRRRQAU
UUUAFFFFABRRRQAUUUUAFFFFABRRRQAUUUUAFFFFABRRRQAUUUUAFc8sLjxY0u3935Sru99xroeg
JrFVpf7fKbR5GAQ+f4u4/lQBtUVEWLfKnTu1Hk45DHdQAk7cBM8seQPSpdoXGBTUjEfufU0+gAoo
ooA8sooorUAooooAKKKKACiiigAooooAKKKKACiiigApVZlYFTtPXI60lFAFy81KS8t4YpAp8sbQ
38X41UpKKACiiigAooooAKKKKACiiigAooooAKKKKACtD4T/APInt/2FNT/9L56z60PhP/yJ7f8A
YU1P/wBL5687Hfw16nbhPjfodhRRRXhnrBRRRQAVy/xI/wCRetP+wxpX/pwt66iuX+JH/IvWn/YY
0r/04W9XD4kTL4WdRRRRUFBRRRQAUUUUAcvp3/JUPEH/AGB9N/8AR99XUVy+nf8AJUPEH/YH03/0
ffV1FXLf7iY7BRRRUFBRRRQAVy/w3/5F67/7DGq/+nC4rqK5f4b/APIvXf8A2GNV/wDThcVX2WR9
pHUUUUVJYUUUUAFcv8SP+RetP+wxpX/pwt66iuX+JH/IvWn/AGGNK/8AThb1cPiRMvhZ1FFFFQUF
FFFABRRRQBy+nf8AJUPEH/YH03/0ffV1Fcvp3/JUPEH/AGB9N/8AR99XUVct/uJjsFFFFQUFFFFA
BWP8Jf8Aklfgz/sC2X/ohK2Kx/hL/wAkr8Gf9gWy/wDRCV6mB+18v1PNxn2fmdXRRRXqHnBRRRQA
UUUUAFFFFABRRRQAUUUUAFFFFABRRRQAUUUUAFFFFABRRRQAUUUUAFFFFABRRRQAUUUUAFFFFABR
RRQAUUUUAFFFFABRRRQAUUUUAFFFFABRRRQAUUUUAFFFFABRRRQAUUUUAFFFFABRRRQAUUUUAFFF
FABRRRQAUUUUAFFFFABRRRQAVzzXT/8ACRvbjHl+Urj1ySR/Suhrnfs7/wDCTSTH/V+Uq/jkn+tA
HQRLtjX6U6mQ58tfan0AFFFFABRRRQB5ZRRRWoBRRRQAUUUUAFFFFABRRRQAUUUUAFFFFABRRRQA
UUUUAFFKp2sDjPtU9xDuUzxIywduc49RQBXooooAKKKKACiiigAooooAKKKKACsrw3q3iXwrp82n
waNpN9B9su7iOeTVZYWZZbiSUAoLZgCBJj7x6Vq0VnUpxqq00XCcqbvEP+E58V/9C3o//g7l/wDk
Sj/hOfFf/Qt6P/4O5f8A5EoorD6pR/l/M2+sVe4f8Jz4r/6FvR//AAdy/wDyJR/wnPiv/oW9H/8A
B3L/APIlFFH1Sj/L+YfWKvcP+E58V/8AQt6P/wCDuX/5ErK8Sa94r8QafDa/2Fo9v5d5aXe7+2ZW
z5NxHNtx9lH3vL257ZzzjFatFCwtFO6X5i+sVX1D/hOfFf8A0Lej/wDg7l/+RKP+E58V/wDQt6P/
AODuX/5Eooo+qUf5fzH9Yq9w/wCE58V/9C3o/wD4O5f/AJEo/wCE58V/9C3o/wD4O5f/AJEooo+q
Uf5fzD6xV7h/wnPiv/oW9H/8Hcv/AMiUf8Jz4r/6FvR//B3L/wDIlFFH1Sj/AC/mH1ir3Mq317xX
b+KNQ1j+wtHb7XZ21p5P9syjb5Tzvu3fZec+fjGONvfPGr/wnPiv/oW9H/8AB3L/APIlFFH1Wi+n
5i+sVe4f8Jz4r/6FvRv/AAdy/wDyJR/wnPiv/oW9H/8AB3L/APIlFFH1Sj/L+Y/rFXuH/Cc+K/8A
oW9H/wDB3L/8iUf8Jz4r/wChb0f/AMHcv/yJRRR9Uo/y/mH1ir3D/hOfFf8A0Lej/wDg7l/+RKyv
DeveK/D+nzWv9haPceZeXd3u/tmVcedcSTbcfZT93zNue+M8ZxWrRR9Vo7W/MX1ipvcP+E58V/8A
Qt6P/wCDuX/5Eo/4TnxX/wBC3o//AIO5f/kSiij6pR/l/Mf1ir3D/hOfFf8A0Lej/wDg7l/+RKP+
E58V/wDQt6P/AODuX/5Eooo+qUf5fzD6xV7h/wAJz4r/AOhb0f8A8Hcv/wAiVleJNe8V+INPhtf7
C0e38u8tLvd/bMrZ8m4jm24+yj73l7c9s55xitWihYWindL8xfWKr6h/wnPiv/oW9H/8Hcv/AMiU
f8Jz4r/6FvR//B3L/wDIlFFH1Sj/AC/mP6xV7h/wnPiv/oW9H/8AB3L/APIlH/Cc+K/+hb0f/wAH
cv8A8iUUUfVKP8v5h9Yq9w/4TnxX/wBC3o//AIO5f/kSj/hOfFf/AELej/8Ag7l/+RKKKPqlH+X8
w+sVe5l6Hrniq/8AiBrs0Gh6MZ/7LsEkjfWJgqqJbwqQ32UkkktkYGMDk5IHWf2j41/6F/Qf/B7P
/wDIdY/gb/koHiT/ALBenf8Ao29r0CvIxCjCo4pbf5Ho0W5QUmzl/wC0fGv/AEL+g/8Ag9n/APkO
j+0fGv8A0L+g/wDg9n/+Q66iiufmXY3s+5y/9o+Nf+hf0H/wez//ACHR/aPjX/oX9B/8Hs//AMh1
1FFHMuwWfc5f+0fGv/Qv6D/4PZ//AJDrQ+Ev/JK/Bn/YFsv/AEQlbFY/wlwfhX4Mwf8AmC2Wf+/C
V6WCd+bTsedi/snV0UUV6Z54UUUUAFFFFABRRRQAUUUUAFFFFABRRRQAUUUUAFFFFABRRRQAUUUU
AFFFFABRRRQAUUUUAFFFFABRRRQAUUUUAFFFFABRRRQAUUUUAFFFFABRRRQAUUUUAFFFFABRRRQA
UUUUAFFFFABRRRQAUUUUAFFFFABRRRQAUUUUAFFFFABRRRQAUUUUAFYarK2uMcr9mwPruyc/pitq
RiqEj0rnred28SeUW/d+Wr7cDqWOT+lAHR4C8DpmiiigAooooAKKKKAPLKKKK1AKKKKACiiigAoo
ooAKKKKACiiigAooooAKKKKACiiigArT0ORZLhrSRcx3A2n2bsazKfDI0MiyIcMpyPrQBLf2bWN5
JbsclT/+qq9TXNxLdSGaU7mbq3r6VDQAUUUUAFFFFABRRRQAUUUUAFFFFABRRRQAUUUUAFFFFABR
RRQAUUUUAFFFFABRRRQAUUUUAFFFFABRRRQAUUUUAFFFFABRRRQAUUUUAFFFFABRRRQAeBv+SgeJ
P+wXp3/o29r0CvP/AAN/yUDxJ/2C9O/9G3tegV87iv40v66HtYf+EgooorkOkKKKKACvKPhjqNzZ
+AfDBhmdf+JXa8Z4/wBUvavV68f+Hf8AyT/wz/2C7X/0UtetgPtfL9TzcZ9n5noEPjK7jUB445Pc
8GtC38aQNgTRNGfUciuPor1rI846+48aQq2IoWf3NRf8Jt62361ytFFkB2dj4vguJQkyGEMcBuor
oB83Qe9eW/8A663NH8TSWOI7gmWHsT1FJxA7b6UVWtdSt75QYZVc9wDyKs/TmoAKKPWigAoo9aKA
CiiigAooooAKKKKACiiigAooooAKKKKACiiigAooooAKKKKACiiigAooooAKKKKACiiigAooooAK
KKKACiiigAooooAKKKKACiiigAooooAKKKKACiiigAooooAKKKKACiiigAooooAKKKKACiiigAoo
ooAP1HSuehtWXxE1xn5CgQD6En+tdDWGEm/tppA+YcYCY/i7mgDcopqSeYuadQAUUUUAFFFFAHll
FFFagFFFFABRRRQAUUUUAFFFFABRRRQAUUUUAFFFFABRRRQAUUUUAG7jAPHTGaOn4VYsYVuLyKJi
VDMBmnanYnTrySAncFPDe1AFWilPU0lABRRRQAUUUUAFFFFABRRRQAUUUUAFFFFABRRRQAUUUUAF
FFFABRRRQAUUUUAFFFFABRRRQAUUUUAFFFFABRRRQAUUUUAFFFFABRRRQAUUUUAZWg+KtE8M/EDX
f7Y1iw0nz9LsPK+3XSQ+ZtlvN23cRnGRnHqK63/hangr/ocNB/8ABnB/8VWPRXBVwiqzc29zrp4h
04qKRsf8LU8Ff9DhoP8A4M4P/iqP+FqeCv8AocNB/wDBnB/8VWPRWX1CP8xp9bl2Nj/hangr/ocN
B/8ABnB/8VR/wtTwV/0OGg/+DOD/AOKrHoo+oR/mD63LsbH/AAtTwV/0OGg/+DOD/wCKrh/h3/yT
/wAM/wDYLtf/AEUtdBRXVQw6oXs73MKtZ1bXWwUUUV1HOFFFFABS0lFAD4ZngkWSNtrryCDXR2fj
R1wtzD5gx95eDXM0UPUD0Gz8Q2V4oxOqH+7Jxj8auSXkEMYd5UCt0+Yc15l+FOLNwNxx161PKB6d
HJ5i7uMdsGn151p+sXOmyExOdp6oxyK6vT/FVtdGJJB5chUk7uAPxpNAbVFNjkWVQyMHU9CpzTqk
AooooAKKKKACiiigAooooAKKKKACiiigAooooAKKKKACiiigAooooAKKKKACiiigAooooAKKKKAC
iiigAooooAKKKKACiiigAooooAKKKKACiiigAooooAKKKKACiiigAooooAKKKKACiiigAooooAK5
yKV/+EqaMMfL8sEL2zuYV0dYMdp/xURuN3G0R4+jE/1oA2W/csWAyp609ZFfofw707rTWjVu3Pt1
pgOoqOFjtOTuUHjNSUgCiiigDyyiiitQCiiigAooooAKKKKACiiigAooooAKKKKACiiigAooooAK
KKKAJIJjDMkiD5lORUmoXjaheSXDf8tG6egqvRQAp6mkoooAKKKKACiiigAooooAKKKKACiiigAo
oooAKKKKACiiigAooooAKKKKACiiigAooooAKKKKACiiigAooooAKKKKACiiigAooooAKKKKACii
igAooooAKKKKACiiigAooooAKKKKACiiigAooooAKKKKACiiigAooooA19F8QyaXmN182A/w9CK6
zT9ds9RwEkCyf3H4NeeU5XKkEHBHQilZAem/aIvNEXmL5uPu55qTpzx7V5pb301vcrOj/vR/ExzW
zf8Aik32miJVaG4J+ZlPBqeUDsdwyRkbuuM0vWsjQbWOTT45HJllYbmfceM9vyqxJqNvY3EcJlXa
x2qo5K8dTSsBfoo9ulH6UgCiiigAooooAKKKKACiiigAooooAKKKKACiiigAooooAKKKKACiiigA
ooooAKKKKACiiigAooooAKKKKACiiigAooooAKKKKACiiigAooooAKKKKACiiigAooooAKKKRs7f
l5agBaKZGxYdMY60+gArDjhb+3jN5h24CeXjjOSc/r+lblc3Ezf8Je65O3ylOM8feagDpaSlpKAI
lzB8rAlOxHJp4kVujA06mNGjfeUfhQA+io/Ix91ytFAHmFFFFagFFFFABRRRQAUUUUAFFFFABRRR
QAUUUUAFFFFABRRRQAUUUUAFFFFABRRRQAUUUUAFFFFABRRRQAUUUUAFFFFABRRRQAUUUUAFFFFA
BRRRQAUUUUAFFFFABRRRQAUUUUAFFFFABRRRQAUUUUAFFFFABRRRQAUUUUAFFFFABRRRQAUUUUAF
FFFABRRRQAUUUUAFFFFABRRRQAUUUUAFFFFABRRRQAUUUUAFFFFAFi3vri1VlimZFbqAahLszbix
LepPNNooA3dP8WXNpH5cgFwo6HuPrVvT/FclzfhZiscJPG0Vy/8AOilYD077VA0gjWVSxGdual/z
ivL1kdWDh2BXocnIrVk8UXzxxokgj2jBIHLfXNTygd3/ADorlbPxltgxcxF5QcDbxmug07UItUth
ND06MD2NK1gLVFFFIAooooAKKKKACiiigAooooAKKKKACiiigAooooAKKKKACiiigAooooAKKKKA
CiiigAooooAKKKKACiiigAooooAKKKKACiiigAooooAKKKKACiiigCI/LNxznqKlqOP/AFz1JQAe
lYUVsv8AwkBuNx3EBNv0JP8AWt31rDjt1/t4z7juIC7M8AAnn60AbtJS0lABRRRQAUUUUAeWUUUV
qAUUUUAFFFFABRRRQAUUUUAFFFFABRRRQAUUUUAFFFFABRRRQAUUUUAFFFFABRRRQAUUUUAFFFFA
BRRRQAUUUUAFFFFABRRRQAUUUUAFFFFABRRRQAUUUUAFFFFABRRRQAUUUUAFFFFABRRRQAUUUUAF
FFFABRRRQAUUUUAFFFFABRRRQAUUUUAFFFFABRRRQAUUUUAFFFFABRRRQAUUUUAFFFFABRRRQAUU
UUAFFFFABRRRQAUUUUAHPHNauh62+kybSN0DH5l/rWVRQB6FJr1lHbCfzgY84461fhlS4jWSNgyt
yCK8uyfpmrcOqXNvaPbRylYm6gdanlA9IyOxzRWD4d1SD7KkT3GZ8fdkOPyreqQCijNFIAooooAK
KKKACiiigAooooAKKKKACiiigAooooAKKKKACiiigAooooAKKKKACiiigAooooAKKKKACiiigAoo
ooAKKKKACiiigAoopkkwUHBBboKAEj5eRu2cVJTI12xgU+gArmof+Rwf/rkv/oTc10tYcVvGNfM2
f3uAmPYE80AbtJS0lABRRRQAUUUUAeWUUUVqAUUUUAFFFFABRRRQAUUUUAFFFFABRRRQAUUUUAFF
FFABRRRQAUUUUAFFFH4ZoAWkrbk8N/Z9HN5JKRJjOysXH4dqAEooooAKKKKACiiigAooooAKKKKA
CiiigAopa7rRtHgTTIvMhVpGX5t3vQBwlFX9ct4bTUpY4GBQHjH+fWqFABRRRQAUUUUAFFFFABRR
RQAUUUUAFFFFABRRRQAUUUd6ACirtro95dwNNFCWRerZAqn0JB60AJRRRQAUUUUAFFFFABRRRQAU
UUUAFFFFABRRRQAUUUUAFFFFABRRRQAUUUUAFFFFABRRRQAUUUUAFFFFABRRRQAUUUUAFFFFABRR
RQAv04q/a63d27Rjz38tTkrntWfS0Ael2V5Hf26SxNuDCp64vwjbzSXjSI22GP7y59f/ANVdp7g8
Gs2rAFFFFIAooooAKKKKACiiigAooooAKKKKACiiigAooooAKKKKACiiigAooooAKKKKACiiigAo
oooAKKKKACiiigAooooAKD78UVDLKCjKmScelACyN5p2rnH8RFPWNV6ClUBQBjGRS0wCiiikAVhR
Rxf8JAZM/v8AAXbu/hySDj6k1u1zUXHjGT/riv8A6E1AHTUlLSUAFFFFABRRRQB5ZRRRWoBRRRQA
UUUUAFFFFABRRRQAUUUUAFFFFABRRRQAUUUUAFFFFABRRRQAUqttYGkooA09S16fUYUhYCOJQPlH
cis2kooAKKKKACiiigAooooAKKKKACiiigApaSigC/otmt9qUMTD5Ccmu6v5lsdOlcfdjTArA8E2
w/fzEZPCqfTrn+lXvFtx5Wl7c4MjbanqBxDEsdxOc0lFFUAUUUUAFFFFABRRRQAUUUUAFFFFABRR
RQAUUUUAFXNJ8r7fE08bSxKcsqjP4n8cVTrc8Jv5d87Efu9hDcZoAseINWF1ElvY7jEvLmNCMex9
q5xlK9QQevNelw2kEbSSRxgeZ97jGazPEmli6sSYYVMykHKjBxU3A4ailZdrEHIxwQeuaSqAKKKK
ACiiigAooooAKKKKACiiigAooooAKKKKACiiigAooooAKKKKACiiigAooooAKKKKACiiigAooooA
KKKKACiiigAooooAKKKKAJ7e8ltY5UjYhZRtYCtKz8UXlnD5XyyAfdJ7VjUUAbVp4ou47wSTy74i
fmjxwB7V2tvcR3UKyxsHRhw39K8wrV0PXH0uQKwLW7feX0+lJoDvqKihuoriJXjkVlbpzUtZgFFF
FABRRRQAUUUUAFFFFABRRRQAUUUUAFFFFABRRRQAUUUUAFFFFABRRRQAUUUUAFFFFABRRRQAUUVH
5jMSEUEepNACTZZ1Q9Dk1IqhRxTUjbduc/N2ANPpsAooopAFFFFAB/8AqrEVYv8AhIC2R55UAj/Z
yf8A69bdYcfk/wBvHp9pwM+u3Jx+uaAN2kpaSgAooooAKKKKAPLKKKK1AKKKKACiiigAooooAKKK
KACiiigAooooAKKKKACiiigAooooAKKKKACiiigAooooAKKKKACiiigAoopaAK95fW2nw+bd3EVr
Fnb5kzhFz6ZNR2OsWGqM4s722uyn3hBMrkfXB4qW70mx1iNbfULO2vYg25Uu7dJkDAHB2MCCea4X
4bLD4T+H/g1rDS9Lhk1zxHdaZdzx2aRyMp1G6UHcgB+VQAASQMdKVwPT9H0qTVroRj5UByze1V9a
ii0eaXzZVjhQbi8jABV9zVX4e+NLiS38fm7+x2kGhXiwQzSblG026S7pDnplu2OK8V+JXji+8U+B
/iPY3moadqoi0Ka+S602zlt4ijfJtxI7FuW68UX1A9tBB5ByKKnvEWOYqihVCrhVGAPlFOsbZ57q
BQpw7AZxxTA7bw7Z/YdLTd95zvIrE8aXG65hhBztBY/j/wDqrobzVrbTY/3ki+YFwFHsK4C6umvL
iSVzlmOalb3AhoooqgCiiigAooooAKKKKACiiigAooooAKKKKAFHp37VPNY3FqqvLEyI3Q1e0m0s
2ja5uZ+YuTD/ABGjXdebVtiLH5cSHKj196AMoKWYL39a6fSfD9xb3TyGRoY0YYx/GM1S8J2P2nUA
7RhokBzuHHSu4Gf0qZMBhnTcAWwT60kk8caFndQvTOaIyMbev1pk1jb3ClZIlZT14qAOJ8SSI2pN
siWPAwSjZB96ya7bVPCtvebnhPkycHp8vArjJoWt5XjkG11OCK0QDKKKKYBRRRQAUUUUAFFFFABR
RRQAUUUUAFFFFABRRRQAUUUUAFFFFABRRRQAUUUUAFFFFABRRRQAUUUUAFFFFABRRRQAUUUUAFFF
FABRRRQAUv8AOkooAlgklEiLG7Bt42gH3r0yPPlrnriuB8NosmsW4YZAyfyHFegVEgCiiipAKKKK
ACiiigAooooAKKKKACiiigAooooAKKKKACiiigAooooAKKKKACiiigAooooAKX3pKbJJ5akigBkk
m7KqOe5qRRtAA4pI12L655NOoAKKKKACiiigAooooAK5qH/kcG9fJX/0Jq6WsOOSH+3ynHn4B/4D
k4/XNAG7SUtJQAUUUUAFFFFAHllFFFagFFFFABRRRQAUUUUAFFFFABRRRQAUUUUAFFFFABRRRQAU
UUUAFFFFABRRRQAUUUUAFFFFABRRRQAUUUUAKrFWBHBq9pXwv0m48B6Volvf3Ub6ffyapb3ilDLD
cPPJPkArt4aVgAQeAM5qhXS+EU2q8kbYfzAGTP8AD60mByOpfCzTtJ0Hxfolxcahqtt4pdpr+ed1
VhmFYjt2KAvC5xXOa78MbLxBb+IV1LX9a1W61rSv7ImubloVEcW8NlERAqnjHTnvmvbfEEDz6eUi
UGRyBz7muCnge2meKQYdDgikgH3DpdXRKBlRiAA3XHArs7i6t/D+lx4VWkC/IMc5PeuS0eze8vol
VGZVYMxXsAetS+ILhrjUpRksiHaoJpgUbid7qZpZDudjkmo6P0opgFFFFABRRRQAUUUUAFFFFABR
RRQAUUUUALT4YWuJkjUZZjgVHWp4f0tNVumjd2VVXIK+tAG5L4Oga1RVcrOo5PYn0rEt9Gkj1ZLS
5RsHAJXnitW81m98PuLaTZc4GVdhgj8qs2PiZGsXnulVW3bVWM8n8KnUDbt7WO0hCQqI1AqXoOOt
QWt7HdRK6ZwR6YqeoAbIu7kDmgSKcDPNOpHjWQYIDd+RQBS1i6az02WaNgGXgN715/cXUl5M0srb
pGPOMc132oWFvc2L+YoUKC2MkAH1rz3j8KuICUUUVQBRRRQAUUUUAFFFFABRRRQAUUUUAFFFFABR
RRQAUUUUAFFFFABRRRQAUUUUAFFFFABRRRQAUUUUAFFFFABRRRQAUUUUAFFFFABRRRQAUUUUAWtO
uTZ3kMo52MOnpmvRhKvlh2IUEZ5ry/0/L3qee+uLmNI5JWdV6KTxSauB6UkiyLuUhh6inVjeE0WP
SFCsGyxJx26cVs1ABRRRSAKKKKACiiigAooooAKKKKACiiigAooooAKKKKACiiigAooooAKKKKAC
iiigAqK4Qsuc8DtUtNlk8tckZyMAUwFXGBjpS02NSkag9adSAKKKKACiiigAooooAKwopYv+EgMW
B5+A27H8OTgZ+ua3a5qL/kcHP/TFf/QmoA6akpaSgAooooAKKKKAPLKKKK1AKKKKACiiigAooooA
KKKKACiiigAooooAKKKKACiiigAooooAKKKKACiiigAooooAKKKKACiiigAooooAK6fwhp7t5lwW
wn3NvvXM/rXQeHdYNvG1sdqoAXMjN3xxSewHYsB3HHBrz/xFIkurTmNsjofqOtdh/aKw6Wsssqeb
5QPXuR2rz/cZH4BLE8Z6mlEDtPC+lrbWYuGBWWUYyfTtXJ6nD9n1C4j3btrkZrpdcvDpOlxWkMhL
sMBs8gVyJ6knJPcmmu4CUUUUwCiiigAooooAKKKKACiiigAooooAKKKKACr2l6rLpMrvEFbcMEGq
NFAFrUL59Sn86VVDY7CrWg6bLfXHmR7CITuKseo/wrNjxuG/pnmvQNFjsFhLWW3B+8R978aT0A0e
nbHfAFFFIzBR0yazAXn8KOvGaiknMKksjbRz8vb3qkmqRJK7SRyImQok8s7WHrnt1oATWdJl1NMR
3LQ8Y29j9a4a9tTY3MkDMCU4+Wu18QTXFnHHdwE7Y/vLzgg9DXE3V1JeTtLKQZG64q4gQ0UUVQBR
RRQAUUUUAFFFFABRRRQAUUUUAFFFFABRRRQAUUUUAFFFFABRRRQAUUUUAFFFFABRRRQAUUUUAFFF
FABRRRQAUUUUAFFFFABRRRQAUUUUAFLSUUAaGn61d6apSF8I3JU8j8q7HQ9XGrWu48Spwy+npxXn
1dF4Pvobe4likba0oG0/TP8AjSaA7Gij0orMAooooAKKKKACiiigAooooAKKKKACiiigAooooAKK
KKACiiigAooooAKKKKACopkDAP3U1LRQAisHXIOaWophtwy/ePFS+tABRRRQAUUUUAFFFFAB79hW
HFcJ/b5hwfNADk4/hJOP61uVhx3S/wBvm32tvAEm72JIx+lAG7SUtJQAUUUUAFFFFAHllFFFagFF
FFABRRRQAUUUUAFFFFABRRRQAUUUUAFFFFABRRRQAUUUUAFFFFABRRRQAUUUUAFFFFABRRRQAUUU
UAFLSUUAKWLdSTU1nMtvMJCM7R8v17frUFHrQBJNPJcNvkYsx9TUdFFABRRRQAUUUUAFFFFABRRR
QAUUUUAFFFFABRRS0ALHG00iogJZjgAVJ9jm85oRGzSqeVUZrW8Iw+Zqu4j5VUnn8K7KO1ihkaRE
VZGPzMOppN2A8yZSpKt8rKcHPrXd+G4IrPTUIdWkYbmwRWY2ixDXCN4nkZzIYSMYGcnNdMLeIbRs
XC9BjpSbAVZkcZVg2elKq46nJpQoXkDmlqAAjd1NRXVql5bvA/3XGMipaKAOOv1v9Bt2g3Ca0kBw
W5K1zvr375r0+aCOeNlkUMrDBzXn+taY2l3zRcFW+ZfpWiYFCiiimAUUUUAFFFFABRRRQAUUUUAF
FFFABRRRQAUUUUAFFFFABRRRQAUUUUAFFFFABRRRQAUUUUAFFFFABRRRQAUUUUAFFFFABRRRQAUU
UUAFFFFABRRRQAU5GKMGBwQc5ptFAHomiagNS0+OQ/6wfK49CP8A62Kv1w3hfUGtNQWIn93N8pHY
H1rue/8Anis2AUUUUgCiiigAooooAKKKKACiiigAooooAKKKKACiiigAooooAKKKKACiiigAoooo
Ajm6x/739DUlQsxmYKowVOamoAKKKKACiiigAooooAK5qFT/AMJcxwdvlLz/AMCbiulrDjmP/CQG
Hyz0D+Zjjknj9KAN2kpaSgAooo55oAKKQ8UUAeW0UUVqAUUUUAFFFFABRRRQAUUUUAFFFFABRRRQ
AUUUUAFFFFABRRRQAUUUUAFFFFABRRRQAUUUUAFFFFABRRRQAUUUUAFFFFABRRRQAUUUUAFFFFAB
RRRQAUUUUAFFFFABRRRQAUv1pKXv7UAaejyXdgxvYYTJCMq9dLo+pXuqXDTNGsdl0XPUmszwbcCT
7RaPkow3Afz/AKVqNpN7aQtHZXSpHnKxumdoPoalgQXOlXNnq4voWMyM43xjlgPT3rfjdZlDKcqa
rWN0Zo/Lm+W4jADr/WoLyaew8wxQBoMbic8j14qQNGisObxZbxOgMUgZj8wYYxW5ncuR0pAFFFFA
EU1wIRyCzdlXmuC164muNSkMy+WVx8uc4GK9AKrHlsc92rzjU5zcahcvndmQgN6j/wDVVRAq0UUV
YBRRRQAUUUUAFFFFABRRRQAUUUUAFFFFABRRRQAUUUUAFFFFABRRRQAUUUUAFFFFABRRRQAUUUUA
FFFFABRRRQAUUUUAFFFFABRRRQAUUUUAFFFFABRRRQA5WZGBU4YHIr0LRNS/tSxSUjD9G+o7153X
ceEZhJpO0DmNiD+POf1qZAbdFFFQAUUUUAFFFFABRRRQAUUUUAFFFFABRRRQAUUUUAFFFFABRRRQ
AUUUUAFGcZNFFAEKZkkDY2gZ/GphwMVHF8ruh/3qkpgFFFFIAooooAKKKKACsCK7J8RPbbeFUSbs
+pIx+lbxrnLeNv8AhKZ5CPk8tVDe+5j/AFoA6SkZ1TGTilbjNRrmVt+BjHGRQA7zU6FhTGmLfKoP
1xxT1iReiilx6cUwI/J3fecn6cUVLRSA8sooorUAooooAKKKKACiiigAooooAKKKKACiiigAoooo
AKKKKACiiigAooooAKKKKACiiigAooooAKKKKACiiigAooooAKKKKACiiigAooooAKKKKACiiigA
ooooAKKKKACiiigApaSigDU8N3Bt9Xgx0clD/n8K7/0+lcN4VtftGqK+cCMbq7nrUS3AjkTGXTak
o/ixWRpOum8mnimKNsJw6ggEevWtp13KQeM8VxraTPo+owqxLWkjqGK/xDPQ0IDd1DQ7fV5EmYNG
3QsvU+lWpDPaeWPle3UfvHb72ParSsCBj9Kcy5BBGc8dM1IEVrdJeR+ZGSy5wDUtZF5Be2MZNiU8
lTuMTDkeuKxb7xdcyALCPIOMMe+adgNzxDqkdlYyIH/fuMKM1wXT/P61JcXEl1MZZXLueparGj6f
/aV8kG7C5yfpVrQDR03w2NR0+ObeySuTjHQCsOSMxSMjdVODXfaleRaDp/yL90YRK4GRjI7M33ic
mhANooopgFFFFABRRRQAUUUUAFFFFABRRRQAUUUUAFFFFABRRRQAUUUUAFFFFABRRRQAUUUUAFFF
FABRRRQAUUUUAFFFFABRRRQAUUUUAFFFFABRRRQAUUUUAFb3hLUBbXzQuTtmGB9e1YX1qxp959hv
Iptu7aQSKAPSqKq6fqUOpQCWE8Ecr6VarIAooooAKKKKACiiigAooooAKKKKACiiigAooooAKKKK
ACiiigAooooAKKKKAIpPllQ+vBqWo5lZtpA3YPIpY5CxYEYINAD6KKKACiiigAooo9aAGSTLChZj
gVi2c7yaxIpTEAG5X+vaneKrqWGz8uOEzb/lIU4xnvS+HoP9FRZtryIgGQeOOKANUSM7MEQYz95q
fCmxME84/CnbQOANvfiigAooooAKKKKAPLKKKK1AKKKKACiiigAooooAKKKKACiiigAooooAKKKK
ACiiigAooooAKKKKACiiigAooooAKKKKACiiigAooooAKKKKACiiigAooooAKKKKACiiigAooooA
KKKKACiiigAooooAKKKWgDa8MySWc8lztJt1+Vz9e/6VvR6+moXUcNocAHJ3jlh6Cm+FIlOjkMoZ
XYggjIIqxqunwrZvLDEFlRf3ZUfd+lQ9wNTv/PNFR2277PGJOX2jd9cVJUgRzRswBQ7HXo3aoLe6
d7qS3kB3oN25ehzVv371jaxq0Ol3UJYsrn72BwVoA1Li4itYjLMwVB61599lfUtQlS0QsC2Rnp1r
S8Sa5FqUaQwAhM5ZiMH6VR0PUpdPvk2HCOwDirSAm1Lw3c6dEsvEi4+bb2PpUPh+aO31SKSWQRoB
wxHrXeXDw42Ssilgcbj2rmND0mykmllkl8zy3YCM9Dg0XAh8YXaz3USRyblVeg9awKt6pcRXV9I8
KLHHnChRgH3qn9KoAooooAKKKKACiiigAooooAKKKKACiiigAooooAKKKKACiiigAooooAKKKKAC
iiigAooooAKKKKACiiigAooooAKKKKACiiigAooooAKKKKACiiigAooooAKWkooAtWGoTabcCSI4
fuvZq7vSdYh1aEFDiUfeTuted1La3UlpOssbFWU9jSauB6bRVLSdUTVLXzV++PvqO1XazAKKKKAC
iiigAooooAKKKKACiiigAooooAKKKKACiiigAooooAKKKKAD6daih+XeOpz1qXpUdv8A6snuSafQ
CSiiikAUUUUAFH1opGcLyWAA9xQBx+tyEaq0F0d9pOMccYYHgfjXTafEkcClPTGB29qx38y41OVj
IskJxtXuDk5P8q3reHyVxnk0AS0UUUAFFFFABRRRQB5ZRRRWoBRRRQAUUUUAFFFFABRRRQAUUUUA
FFFFABRRRQAUUUtACUVPZ2/2q4WMttBJGfyourb7OxG7d+FAEFFFFABRRRQAUUUUAFFFFABRRRQA
UUUUAFFFFABRRRQAUUUUAFFFFABRRRQAUUUUAFFFFABRRRQAUUUUAFFFKOoFAHe+GU26PAfXJrVI
DcGs/QBt0a191P8AOtCs3uBHB9zBPQ/xfXipKZJGJPY+tPpAH86y9a0+2uIxNdSskUfJUMcH2qxq
lxJa2okjOCrAfWub8TavJcf6LtCoMMTnrxTQHPSBRI2z7ueDSZIwRwfWjqw+lSWaCa6iQ9CwBrQD
ppPDL3mmxS+cz3LDcNzdj2rl2V7d2QnYVO07a9Evv9H0uXyztKR4B+leclizFicksSTUxATtiiii
qAKKKKACiiigAooooAKKKKACiiigAooooAKKKKACiiigAooooAKKKKACiiigAooooAKKKKACiiig
AooooAKKKKACiiigAooooAKKKKACiiigAooooAKKKKACiiigAooooAs2OoT6fJvgfaT27V6Fp919
tsoZ8Y3rmvNlHzfiK9MtY1jt4kUYUKMCpkBLRRRUAFFFFABRRRQAUUUUAFFFFABRRRQAUUUUAFFF
FABRRRQAUUUUAFRMphbcOUPWpc84qGaQ8IOhoAm/l60UijaoHYUtABRRRQAVialqJuJnsdjgFdxI
Bx6Y/WtzHSuY8RN/xNLFV+UGYZx3+U/40AL4V8O/2bC7suGkcsc8nrwM/wCetdLUVooW3U+v+NS0
AFFFFABRRVLWdQOl6bPdBBIY1ztJxmgC7RXjEHx/uprqWL+x4QEzz559fpRQB//Z</Data></Thumbnail></Binary></metadata>
