<?xml version="1.0" encoding="UTF-8"?>
<metadata xml:lang="en"><Esri><CreaDate>20170505</CreaDate><CreaTime>13095400</CreaTime><ArcGISFormat>1.0</ArcGISFormat><SyncOnce>TRUE</SyncOnce><DataProperties><lineage><Process ToolSource="c:\program files (x86)\arcgis\desktop10.4\ArcToolbox\Toolboxes\Data Management Tools.tbx\CreateFishnet" Date="20170505" Time="130954">CreateFishnet "Q:\SGC_Index_Maps\Working_IndexMaps\Branner General Collection\SULGC_2484254\SULGC_2484254_Orlando.shp" "-84 28" "-84 38" # # 1 1 "-80 30" NO_LABELS "-84 28 -80 30" POLYGON</Process></lineage></DataProperties></Esri></metadata>
